{
"meta":{"test_sets":[],"test_metrics":[],"learn_metrics":[{"best_value":"Min","name":"RMSE"}],"launch_mode":"Train","parameters":"","iteration_count":1000,"learn_sets":["learn"],"name":"experiment"},
"iterations":[
{"learn":[1.732469869],"iteration":0,"passed_time":0.1400471703,"remaining_time":139.9071231},
{"learn":[1.650662238],"iteration":1,"passed_time":0.1623745924,"remaining_time":81.02492161},
{"learn":[1.56548905],"iteration":2,"passed_time":0.204928447,"remaining_time":68.10455388},
{"learn":[1.493318953],"iteration":3,"passed_time":0.235105478,"remaining_time":58.54126402},
{"learn":[1.425623595],"iteration":4,"passed_time":0.2560432008,"remaining_time":50.95259695},
{"learn":[1.353809612],"iteration":5,"passed_time":0.2846706293,"remaining_time":47.16043426},
{"learn":[1.292987686],"iteration":6,"passed_time":0.3065926209,"remaining_time":43.49235322},
{"learn":[1.252994404],"iteration":7,"passed_time":0.3281227135,"remaining_time":40.68721648},
{"learn":[1.201429498],"iteration":8,"passed_time":0.349542056,"remaining_time":38.48846417},
{"learn":[1.142405099],"iteration":9,"passed_time":0.3696672758,"remaining_time":36.59706031},
{"learn":[1.106426844],"iteration":10,"passed_time":0.3909009936,"remaining_time":35.14555297},
{"learn":[1.057804295],"iteration":11,"passed_time":0.4122071786,"remaining_time":33.93839104},
{"learn":[1.023716728],"iteration":12,"passed_time":0.4333697154,"remaining_time":32.90276223},
{"learn":[0.99409294],"iteration":13,"passed_time":0.4541247657,"remaining_time":31.9833585},
{"learn":[0.9650857757],"iteration":14,"passed_time":0.4761486381,"remaining_time":31.2670939},
{"learn":[0.9271415103],"iteration":15,"passed_time":0.4967455324,"remaining_time":30.54985024},
{"learn":[0.8903850013],"iteration":16,"passed_time":0.5174752898,"remaining_time":29.92224764},
{"learn":[0.8613571937],"iteration":17,"passed_time":0.5401511026,"remaining_time":29.46824348},
{"learn":[0.8369796358],"iteration":18,"passed_time":0.5652894523,"remaining_time":29.18678699},
{"learn":[0.8117715114],"iteration":19,"passed_time":0.5876341773,"remaining_time":28.79407469},
{"learn":[0.7889839491],"iteration":20,"passed_time":0.6098879166,"remaining_time":28.43239383},
{"learn":[0.774479196],"iteration":21,"passed_time":0.6247622057,"remaining_time":27.77351987},
{"learn":[0.752688979],"iteration":22,"passed_time":0.6476237167,"remaining_time":27.50992918},
{"learn":[0.7333453503],"iteration":23,"passed_time":0.6717155049,"remaining_time":27.31643053},
{"learn":[0.7192502141],"iteration":24,"passed_time":0.6975266342,"remaining_time":27.20353873},
{"learn":[0.7066079396],"iteration":25,"passed_time":0.7059226271,"remaining_time":26.44494765},
{"learn":[0.6939761824],"iteration":26,"passed_time":0.7323011718,"remaining_time":26.38996445},
{"learn":[0.6812827607],"iteration":27,"passed_time":0.7478013884,"remaining_time":25.95939105},
{"learn":[0.6731981193],"iteration":28,"passed_time":0.760970029,"remaining_time":25.4793758},
{"learn":[0.6673178363],"iteration":29,"passed_time":0.7883391393,"remaining_time":25.48963217},
{"learn":[0.6581178018],"iteration":30,"passed_time":0.79944811,"remaining_time":24.9892006},
{"learn":[0.6505778535],"iteration":31,"passed_time":0.8084043154,"remaining_time":24.45423054},
{"learn":[0.638378013],"iteration":32,"passed_time":0.8318297889,"remaining_time":24.37513351},
{"learn":[0.6288393203],"iteration":33,"passed_time":0.8560587659,"remaining_time":24.32214023},
{"learn":[0.6168749844],"iteration":34,"passed_time":0.8722433015,"remaining_time":24.04899388},
{"learn":[0.6095745803],"iteration":35,"passed_time":0.8882860825,"remaining_time":23.78632732},
{"learn":[0.6001073459],"iteration":36,"passed_time":0.9052396153,"remaining_time":23.56069593},
{"learn":[0.5907903809],"iteration":37,"passed_time":0.9286652592,"remaining_time":23.50989419},
{"learn":[0.5849166592],"iteration":38,"passed_time":0.9544199555,"remaining_time":23.5178866},
{"learn":[0.5789487647],"iteration":39,"passed_time":0.9654894623,"remaining_time":23.17174709},
{"learn":[0.5756960198],"iteration":40,"passed_time":0.9781536637,"remaining_time":22.87925277},
{"learn":[0.5743852045],"iteration":41,"passed_time":0.9865660329,"remaining_time":22.50310142},
{"learn":[0.5632704351],"iteration":42,"passed_time":1.013621289,"remaining_time":22.55896682},
{"learn":[0.556213057],"iteration":43,"passed_time":1.026858087,"remaining_time":22.3108257},
{"learn":[0.5515103258],"iteration":44,"passed_time":1.051803943,"remaining_time":22.32161701},
{"learn":[0.5486782659],"iteration":45,"passed_time":1.067130539,"remaining_time":22.13135944},
{"learn":[0.5397589236],"iteration":46,"passed_time":1.091948858,"remaining_time":22.14100557},
{"learn":[0.5385419886],"iteration":47,"passed_time":1.103861924,"remaining_time":21.89326149},
{"learn":[0.5330863571],"iteration":48,"passed_time":1.127951333,"remaining_time":21.89146363},
{"learn":[0.5296688278],"iteration":49,"passed_time":1.15763064,"remaining_time":21.99498217},
{"learn":[0.520249659],"iteration":50,"passed_time":1.184016149,"remaining_time":22.03198678},
{"learn":[0.5138243877],"iteration":51,"passed_time":1.207827457,"remaining_time":22.01962364},
{"learn":[0.5055670404],"iteration":52,"passed_time":1.232502949,"remaining_time":22.02226968},
{"learn":[0.5013288464],"iteration":53,"passed_time":1.248856069,"remaining_time":21.87810817},
{"learn":[0.4971480372],"iteration":54,"passed_time":1.273587609,"remaining_time":21.88255074},
{"learn":[0.4917551101],"iteration":55,"passed_time":1.298365537,"remaining_time":21.88673333},
{"learn":[0.4887973963],"iteration":56,"passed_time":1.318255652,"remaining_time":21.80903649},
{"learn":[0.4844599075],"iteration":57,"passed_time":1.348969926,"remaining_time":21.90913224},
{"learn":[0.4778749632],"iteration":58,"passed_time":1.372488027,"remaining_time":21.8900209},
{"learn":[0.4735700468],"iteration":59,"passed_time":1.395174836,"remaining_time":21.8577391},
{"learn":[0.4670656223],"iteration":60,"passed_time":1.420436043,"remaining_time":21.86540073},
{"learn":[0.4635917153],"iteration":61,"passed_time":1.436880585,"remaining_time":21.73861272},
{"learn":[0.4608642125],"iteration":62,"passed_time":1.459132682,"remaining_time":21.70170354},
{"learn":[0.4582447745],"iteration":63,"passed_time":1.482026382,"remaining_time":21.67463584},
{"learn":[0.4545184174],"iteration":64,"passed_time":1.502423606,"remaining_time":21.61178572},
{"learn":[0.4511307921],"iteration":65,"passed_time":1.520165852,"remaining_time":21.51265009},
{"learn":[0.4487400163],"iteration":66,"passed_time":1.541709341,"remaining_time":21.46887784},
{"learn":[0.4463249204],"iteration":67,"passed_time":1.562542775,"remaining_time":21.41602745},
{"learn":[0.4427057163],"iteration":68,"passed_time":1.583219004,"remaining_time":21.36198395},
{"learn":[0.4351095726],"iteration":69,"passed_time":1.603874781,"remaining_time":21.30862209},
{"learn":[0.4261325358],"iteration":70,"passed_time":1.625043047,"remaining_time":21.2628872},
{"learn":[0.4240819048],"iteration":71,"passed_time":1.646412257,"remaining_time":21.22042465},
{"learn":[0.4134326582],"iteration":72,"passed_time":1.668809608,"remaining_time":21.19159598},
{"learn":[0.4101152772],"iteration":73,"passed_time":1.689945786,"remaining_time":21.14715943},
{"learn":[0.4011103966],"iteration":74,"passed_time":1.710895254,"remaining_time":21.10104147},
{"learn":[0.3959191761],"iteration":75,"passed_time":1.73396727,"remaining_time":21.08139155},
{"learn":[0.3933347068],"iteration":76,"passed_time":1.750911874,"remaining_time":20.98820337},
{"learn":[0.3907736721],"iteration":77,"passed_time":1.767905865,"remaining_time":20.89755394},
{"learn":[0.3873634138],"iteration":78,"passed_time":1.788494824,"remaining_time":20.85068016},
{"learn":[0.385512865],"iteration":79,"passed_time":1.809253496,"remaining_time":20.80641521},
{"learn":[0.3782032574],"iteration":80,"passed_time":1.832537045,"remaining_time":20.79137709},
{"learn":[0.3751402704],"iteration":81,"passed_time":1.855015512,"remaining_time":20.76712488},
{"learn":[0.3661499403],"iteration":82,"passed_time":1.87552189,"remaining_time":20.72112739},
{"learn":[0.3643241637],"iteration":83,"passed_time":1.896688046,"remaining_time":20.68293155},
{"learn":[0.3625881386],"iteration":84,"passed_time":1.918290624,"remaining_time":20.64983437},
{"learn":[0.3557756175],"iteration":85,"passed_time":1.940475057,"remaining_time":20.62318839},
{"learn":[0.3544575307],"iteration":86,"passed_time":1.958796359,"remaining_time":20.55610432},
{"learn":[0.3527773237],"iteration":87,"passed_time":1.979580331,"remaining_time":20.5156507},
{"learn":[0.3473342326],"iteration":88,"passed_time":2.000199857,"remaining_time":20.47395584},
{"learn":[0.3457178649],"iteration":89,"passed_time":2.02137901,"remaining_time":20.43838777},
{"learn":[0.3395276726],"iteration":90,"passed_time":2.048240947,"remaining_time":20.45990133},
{"learn":[0.3379634262],"iteration":91,"passed_time":2.074132905,"remaining_time":20.47078997},
{"learn":[0.3364701005],"iteration":92,"passed_time":2.094796892,"remaining_time":20.42990087},
{"learn":[0.335044731],"iteration":93,"passed_time":2.115222759,"remaining_time":20.38714702},
{"learn":[0.3290977973],"iteration":94,"passed_time":2.136598953,"remaining_time":20.35391634},
{"learn":[0.3278135023],"iteration":95,"passed_time":2.159160379,"remaining_time":20.33209357},
{"learn":[0.326446934],"iteration":96,"passed_time":2.181165669,"remaining_time":20.30507834},
{"learn":[0.3199753751],"iteration":97,"passed_time":2.202034051,"remaining_time":20.26770116},
{"learn":[0.3186469604],"iteration":98,"passed_time":2.223187504,"remaining_time":20.23325193},
{"learn":[0.3158776933],"iteration":99,"passed_time":2.245448502,"remaining_time":20.20903652},
{"learn":[0.3097576307],"iteration":100,"passed_time":2.269662283,"remaining_time":20.20224151},
{"learn":[0.3085159596],"iteration":101,"passed_time":2.297213555,"remaining_time":20.22448797},
{"learn":[0.3059452568],"iteration":102,"passed_time":2.340614392,"remaining_time":20.38379718},
{"learn":[0.3001593295],"iteration":103,"passed_time":2.364361307,"remaining_time":20.36988203},
{"learn":[0.2989989121],"iteration":104,"passed_time":2.389812738,"remaining_time":20.37030858},
{"learn":[0.2936598502],"iteration":105,"passed_time":2.412439536,"remaining_time":20.34642401},
{"learn":[0.2925355049],"iteration":106,"passed_time":2.433966457,"remaining_time":20.31338361},
{"learn":[0.290150444],"iteration":107,"passed_time":2.455357906,"remaining_time":20.27943752},
{"learn":[0.2850394078],"iteration":108,"passed_time":2.479790265,"remaining_time":20.27057914},
{"learn":[0.2810721734],"iteration":109,"passed_time":2.505370803,"remaining_time":20.2707274},
{"learn":[0.2788869367],"iteration":110,"passed_time":2.526336641,"remaining_time":20.23345292},
{"learn":[0.273868741],"iteration":111,"passed_time":2.548574164,"remaining_time":20.2065523},
{"learn":[0.271794135],"iteration":112,"passed_time":2.573533491,"remaining_time":20.20109917},
{"learn":[0.2673195232],"iteration":113,"passed_time":2.595561793,"remaining_time":20.17252411},
{"learn":[0.2663948611],"iteration":114,"passed_time":2.617000336,"remaining_time":20.13952433},
{"learn":[0.2644210986],"iteration":115,"passed_time":2.63789681,"remaining_time":20.10259293},
{"learn":[0.2602221623],"iteration":116,"passed_time":2.659252014,"remaining_time":20.06939768},
{"learn":[0.2591768653],"iteration":117,"passed_time":2.681179082,"remaining_time":20.04067754},
{"learn":[0.2546616997],"iteration":118,"passed_time":2.701771772,"remaining_time":20.0021927},
{"learn":[0.2537626371],"iteration":119,"passed_time":2.715773507,"remaining_time":19.91567239},
{"learn":[0.2490409075],"iteration":120,"passed_time":2.73645531,"remaining_time":19.87887783},
{"learn":[0.2471745601],"iteration":121,"passed_time":2.757484759,"remaining_time":19.84484933},
{"learn":[0.2430381078],"iteration":122,"passed_time":2.77791185,"remaining_time":19.80673734},
{"learn":[0.242215826],"iteration":123,"passed_time":2.796633158,"remaining_time":19.75686005},
{"learn":[0.237892142],"iteration":124,"passed_time":2.819746333,"remaining_time":19.73822433},
{"learn":[0.23612657],"iteration":125,"passed_time":2.842067085,"remaining_time":19.71402089},
{"learn":[0.2323260759],"iteration":126,"passed_time":2.866622441,"remaining_time":19.7052078},
{"learn":[0.2314201151],"iteration":127,"passed_time":2.889919948,"remaining_time":19.68757964},
{"learn":[0.2283816559],"iteration":128,"passed_time":2.914754641,"remaining_time":19.68024258},
{"learn":[0.224819823],"iteration":129,"passed_time":2.937540886,"remaining_time":19.65892747},
{"learn":[0.2219622949],"iteration":130,"passed_time":2.961623106,"remaining_time":19.64618686},
{"learn":[0.2186335228],"iteration":131,"passed_time":2.983904518,"remaining_time":19.62143274},
{"learn":[0.215942538],"iteration":132,"passed_time":3.005664397,"remaining_time":19.59331603},
{"learn":[0.2151693939],"iteration":133,"passed_time":3.021355057,"remaining_time":19.52607074},
{"learn":[0.2123609537],"iteration":134,"passed_time":3.045422394,"remaining_time":19.513262},
{"learn":[0.2116209496],"iteration":135,"passed_time":3.0607185,"remaining_time":19.44456459},
{"learn":[0.2090899727],"iteration":136,"passed_time":3.085878741,"remaining_time":19.4387836},
{"learn":[0.2064623578],"iteration":137,"passed_time":3.11588558,"remaining_time":19.46299543},
{"learn":[0.2040485314],"iteration":138,"passed_time":3.138566851,"remaining_time":19.44105078},
{"learn":[0.1998860189],"iteration":139,"passed_time":3.163555717,"remaining_time":19.43327083},
{"learn":[0.1990021678],"iteration":140,"passed_time":3.1868563,"remaining_time":19.41496143},
{"learn":[0.1981584967],"iteration":141,"passed_time":3.211016069,"remaining_time":19.40177315},
{"learn":[0.194497829],"iteration":142,"passed_time":3.233743867,"remaining_time":19.37984961},
{"learn":[0.1936799082],"iteration":143,"passed_time":3.258725842,"remaining_time":19.37131473},
{"learn":[0.1928992109],"iteration":144,"passed_time":3.281744355,"remaining_time":19.35097533},
{"learn":[0.1921541642],"iteration":145,"passed_time":3.306616435,"remaining_time":19.34144134},
{"learn":[0.1900193836],"iteration":146,"passed_time":3.34107631,"remaining_time":19.38733396},
{"learn":[0.1866474885],"iteration":147,"passed_time":3.375640682,"remaining_time":19.4327423},
{"learn":[0.1859161769],"iteration":148,"passed_time":3.402617644,"remaining_time":19.43374238},
{"learn":[0.1827565651],"iteration":149,"passed_time":3.429506807,"remaining_time":19.43387191},
{"learn":[0.1816897958],"iteration":150,"passed_time":3.453828232,"remaining_time":19.41920641},
{"learn":[0.1810119711],"iteration":151,"passed_time":3.479081624,"remaining_time":19.40961327},
{"learn":[0.179064091],"iteration":152,"passed_time":3.50531687,"remaining_time":19.40525091},
{"learn":[0.1785118678],"iteration":153,"passed_time":3.526363538,"remaining_time":19.372101},
{"learn":[0.1760761289],"iteration":154,"passed_time":3.558628185,"remaining_time":19.40026333},
{"learn":[0.1736178002],"iteration":155,"passed_time":3.586545491,"remaining_time":19.40413073},
{"learn":[0.1717500114],"iteration":156,"passed_time":3.616054494,"remaining_time":19.41613974},
{"learn":[0.1707936531],"iteration":157,"passed_time":3.641738221,"remaining_time":19.40723786},
{"learn":[0.16901948],"iteration":158,"passed_time":3.667057453,"remaining_time":19.39619697},
{"learn":[0.1681078498],"iteration":159,"passed_time":3.691244582,"remaining_time":19.37903406},
{"learn":[0.1663599719],"iteration":160,"passed_time":3.715442645,"remaining_time":19.36184086},
{"learn":[0.1634509289],"iteration":161,"passed_time":3.740938878,"remaining_time":19.35127642},
{"learn":[0.1609015151],"iteration":162,"passed_time":3.765363193,"remaining_time":19.3350245},
{"learn":[0.1602740899],"iteration":163,"passed_time":3.788942977,"remaining_time":19.31436786},
{"learn":[0.1586559276],"iteration":164,"passed_time":3.816967731,"remaining_time":19.31617003},
{"learn":[0.1580753813],"iteration":165,"passed_time":3.840699162,"remaining_time":19.29604278},
{"learn":[0.1558342303],"iteration":166,"passed_time":3.860634919,"remaining_time":19.25693945},
{"learn":[0.1552734871],"iteration":167,"passed_time":3.881520124,"remaining_time":19.22276633},
{"learn":[0.153028397],"iteration":168,"passed_time":3.902282129,"remaining_time":19.18814467},
{"learn":[0.152486641],"iteration":169,"passed_time":3.922620173,"remaining_time":19.15161614},
{"learn":[0.1516947355],"iteration":170,"passed_time":3.942846764,"remaining_time":19.11473665},
{"learn":[0.1501677047],"iteration":171,"passed_time":3.963623179,"remaining_time":19.08069763},
{"learn":[0.1496680086],"iteration":172,"passed_time":3.984158555,"remaining_time":19.04565968},
{"learn":[0.1475596978],"iteration":173,"passed_time":4.00592133,"remaining_time":19.01661505},
{"learn":[0.1470768667],"iteration":174,"passed_time":4.027959661,"remaining_time":18.98895269},
{"learn":[0.1451552787],"iteration":175,"passed_time":4.048655846,"remaining_time":18.95507055},
{"learn":[0.1442645269],"iteration":176,"passed_time":4.071638023,"remaining_time":18.93196663},
{"learn":[0.1419098851],"iteration":177,"passed_time":4.092515825,"remaining_time":18.89914611},
{"learn":[0.1414574385],"iteration":178,"passed_time":4.113543466,"remaining_time":18.86714629},
{"learn":[0.1404616312],"iteration":179,"passed_time":4.135827533,"remaining_time":18.84099209},
{"learn":[0.1390328125],"iteration":180,"passed_time":4.155898634,"remaining_time":18.8048673},
{"learn":[0.1368580728],"iteration":181,"passed_time":4.176361136,"remaining_time":18.77067807},
{"learn":[0.1364356526],"iteration":182,"passed_time":4.197170021,"remaining_time":18.73818529},
{"learn":[0.134577873],"iteration":183,"passed_time":4.217440388,"remaining_time":18.70343129},
{"learn":[0.1331040833],"iteration":184,"passed_time":4.237978741,"remaining_time":18.67001445},
{"learn":[0.1327931472],"iteration":185,"passed_time":4.252498908,"remaining_time":18.61039845},
{"learn":[0.1308428739],"iteration":186,"passed_time":4.27273311,"remaining_time":18.57610705},
{"learn":[0.1285758573],"iteration":187,"passed_time":4.29326814,"remaining_time":18.54326452},
{"learn":[0.1272622372],"iteration":188,"passed_time":4.314176995,"remaining_time":18.51215631},
{"learn":[0.1254866827],"iteration":189,"passed_time":4.33473152,"remaining_time":18.4796449},
{"learn":[0.1250831307],"iteration":190,"passed_time":4.35720955,"remaining_time":18.45540589},
{"learn":[0.1230198742],"iteration":191,"passed_time":4.383043493,"remaining_time":18.44530803},
{"learn":[0.1217883182],"iteration":192,"passed_time":4.404153839,"remaining_time":18.41529611},
{"learn":[0.1213738406],"iteration":193,"passed_time":4.424957288,"remaining_time":18.3841009},
{"learn":[0.1197458843],"iteration":194,"passed_time":4.445688589,"remaining_time":18.35271443},
{"learn":[0.1180327787],"iteration":195,"passed_time":4.467522891,"remaining_time":18.32596125},
{"learn":[0.1168683332],"iteration":196,"passed_time":4.489666044,"remaining_time":18.30051692},
{"learn":[0.1159260389],"iteration":197,"passed_time":4.511893335,"remaining_time":18.27544674},
{"learn":[0.1144120922],"iteration":198,"passed_time":4.533101215,"remaining_time":18.24630187},
{"learn":[0.1140107612],"iteration":199,"passed_time":4.553566568,"remaining_time":18.21426627},
{"learn":[0.1129261659],"iteration":200,"passed_time":4.57401416,"remaining_time":18.18227519},
{"learn":[0.1124426585],"iteration":201,"passed_time":4.597933808,"remaining_time":18.16411475},
{"learn":[0.1110295853],"iteration":202,"passed_time":4.624953472,"remaining_time":18.15806856},
{"learn":[0.1097017087],"iteration":203,"passed_time":4.648090831,"remaining_time":18.13666814},
{"learn":[0.107971021],"iteration":204,"passed_time":4.674021503,"remaining_time":18.12608339},
{"learn":[0.1075940945],"iteration":205,"passed_time":4.697764847,"remaining_time":18.10691888},
{"learn":[0.1060249429],"iteration":206,"passed_time":4.719515676,"remaining_time":18.08007696},
{"learn":[0.1051079948],"iteration":207,"passed_time":4.740265501,"remaining_time":18.04947249},
{"learn":[0.1039838314],"iteration":208,"passed_time":4.761429454,"remaining_time":18.02052966},
{"learn":[0.1036301511],"iteration":209,"passed_time":4.782478782,"remaining_time":17.9912297},
{"learn":[0.1031732118],"iteration":210,"passed_time":4.803508919,"remaining_time":17.9619362},
{"learn":[0.1028399874],"iteration":211,"passed_time":4.825127413,"remaining_time":17.93490756},
{"learn":[0.1019830773],"iteration":212,"passed_time":4.846099841,"remaining_time":17.9055426},
{"learn":[0.1012575256],"iteration":213,"passed_time":4.866402612,"remaining_time":17.87379651},
{"learn":[0.09994347466],"iteration":214,"passed_time":4.889426411,"remaining_time":17.85209178},
{"learn":[0.09911933696],"iteration":215,"passed_time":4.914865619,"remaining_time":17.83914188},
{"learn":[0.09834174826],"iteration":216,"passed_time":4.935256223,"remaining_time":17.80786001},
{"learn":[0.09802589817],"iteration":217,"passed_time":4.956275566,"remaining_time":17.77893345},
{"learn":[0.09728947361],"iteration":218,"passed_time":4.976283788,"remaining_time":17.74647324},
{"learn":[0.09691968607],"iteration":219,"passed_time":4.996534156,"remaining_time":17.71498473},
{"learn":[0.09568745113],"iteration":220,"passed_time":5.017780966,"remaining_time":17.68711028},
{"learn":[0.09481829234],"iteration":221,"passed_time":5.040654535,"remaining_time":17.66499652},
{"learn":[0.09342073348],"iteration":222,"passed_time":5.062416958,"remaining_time":17.63900438},
{"learn":[0.09285393529],"iteration":223,"passed_time":5.084669793,"remaining_time":17.61474892},
{"learn":[0.09220786297],"iteration":224,"passed_time":5.108328027,"remaining_time":17.59535209},
{"learn":[0.09096433317],"iteration":225,"passed_time":5.134671682,"remaining_time":17.58511452},
{"learn":[0.09065985904],"iteration":226,"passed_time":5.158855745,"remaining_time":17.56738102},
{"learn":[0.09032483737],"iteration":227,"passed_time":5.183906462,"remaining_time":17.55252539},
{"learn":[0.08918800624],"iteration":228,"passed_time":5.207500355,"remaining_time":17.53267587},
{"learn":[0.08803870566],"iteration":229,"passed_time":5.23317776,"remaining_time":17.51976902},
{"learn":[0.08699722919],"iteration":230,"passed_time":5.255915688,"remaining_time":17.49696608},
{"learn":[0.08591693927],"iteration":231,"passed_time":5.280642071,"remaining_time":17.48074617},
{"learn":[0.08496106343],"iteration":232,"passed_time":5.303458606,"remaining_time":17.45816631},
{"learn":[0.08394539939],"iteration":233,"passed_time":5.326450422,"remaining_time":17.43615822},
{"learn":[0.0830665859],"iteration":234,"passed_time":5.350029773,"remaining_time":17.41605437},
{"learn":[0.0821114917],"iteration":235,"passed_time":5.373174403,"remaining_time":17.39451374},
{"learn":[0.08122193898],"iteration":236,"passed_time":5.39935688,"remaining_time":17.38273966},
{"learn":[0.08032777265],"iteration":237,"passed_time":5.423284095,"remaining_time":17.36362387},
{"learn":[0.07951763643],"iteration":238,"passed_time":5.449081465,"remaining_time":17.35042257},
{"learn":[0.07873034926],"iteration":239,"passed_time":5.471910847,"remaining_time":17.32771768},
{"learn":[0.07791212778],"iteration":240,"passed_time":5.498712779,"remaining_time":17.31752282},
{"learn":[0.07716411134],"iteration":241,"passed_time":5.534835173,"remaining_time":17.33638455},
{"learn":[0.07643308157],"iteration":242,"passed_time":5.567371158,"remaining_time":17.34362126},
{"learn":[0.07568498691],"iteration":243,"passed_time":5.61372314,"remaining_time":17.39333891},
{"learn":[0.07501508193],"iteration":244,"passed_time":5.658042706,"remaining_time":17.43600915},
{"learn":[0.07467054394],"iteration":245,"passed_time":5.703612894,"remaining_time":17.48180537},
{"learn":[0.07401128421],"iteration":246,"passed_time":5.750666499,"remaining_time":17.5313841},
{"learn":[0.07368039715],"iteration":247,"passed_time":5.796491344,"remaining_time":17.57645762},
{"learn":[0.07318082786],"iteration":248,"passed_time":5.842818447,"remaining_time":17.62231588},
{"learn":[0.07288319243],"iteration":249,"passed_time":5.887634035,"remaining_time":17.6629021},
{"learn":[0.07197114548],"iteration":250,"passed_time":5.93231466,"remaining_time":17.7024051},
{"learn":[0.07124666011],"iteration":251,"passed_time":5.974260206,"remaining_time":17.73312157},
{"learn":[0.0709585009],"iteration":252,"passed_time":6.017571674,"remaining_time":17.7672966},
{"learn":[0.07027546248],"iteration":253,"passed_time":6.059573014,"remaining_time":17.79701366},
{"learn":[0.06966672384],"iteration":254,"passed_time":6.101061754,"remaining_time":17.82467061},
{"learn":[0.06880927995],"iteration":255,"passed_time":6.144487866,"remaining_time":17.85741786},
{"learn":[0.06838816735],"iteration":256,"passed_time":6.187335902,"remaining_time":17.88790107},
{"learn":[0.06811241871],"iteration":257,"passed_time":6.230758382,"remaining_time":17.91946791},
{"learn":[0.06752247899],"iteration":258,"passed_time":6.272021698,"remaining_time":17.9442783},
{"learn":[0.06725770134],"iteration":259,"passed_time":6.313977649,"remaining_time":17.97055177},
{"learn":[0.06654604543],"iteration":260,"passed_time":6.354964268,"remaining_time":17.99355783},
{"learn":[0.0662909827],"iteration":261,"passed_time":6.396924192,"remaining_time":18.018817},
{"learn":[0.06592549838],"iteration":262,"passed_time":6.458915618,"remaining_time":18.0996989},
{"learn":[0.06568212734],"iteration":263,"passed_time":6.524894194,"remaining_time":18.19061412},
{"learn":[0.06522091929],"iteration":264,"passed_time":6.577606887,"remaining_time":18.24355118},
{"learn":[0.06498751682],"iteration":265,"passed_time":6.621243024,"remaining_time":18.27064804},
{"learn":[0.06455741255],"iteration":266,"passed_time":6.66369036,"remaining_time":18.29395144},
{"learn":[0.06433436409],"iteration":267,"passed_time":6.705531071,"remaining_time":18.31510725},
{"learn":[0.06369311652],"iteration":268,"passed_time":6.756208065,"remaining_time":18.35980705},
{"learn":[0.06304387379],"iteration":269,"passed_time":6.798795248,"remaining_time":18.38192789},
{"learn":[0.06282612205],"iteration":270,"passed_time":6.839487506,"remaining_time":18.39847377},
{"learn":[0.06243877444],"iteration":271,"passed_time":6.877353686,"remaining_time":18.40703487},
{"learn":[0.06183203434],"iteration":272,"passed_time":6.915812803,"remaining_time":18.41683483},
{"learn":[0.06158115648],"iteration":273,"passed_time":6.955401712,"remaining_time":18.42927607},
{"learn":[0.06134353956],"iteration":274,"passed_time":6.997693639,"remaining_time":18.44846505},
{"learn":[0.06080467592],"iteration":275,"passed_time":7.03798685,"remaining_time":18.46196551},
{"learn":[0.0603872247],"iteration":276,"passed_time":7.094129197,"remaining_time":18.51644552},
{"learn":[0.06016753272],"iteration":277,"passed_time":7.134132564,"remaining_time":18.52821479},
{"learn":[0.05982010128],"iteration":278,"passed_time":7.210697219,"remaining_time":18.63409568},
{"learn":[0.05951067445],"iteration":279,"passed_time":7.269053128,"remaining_time":18.6918509},
{"learn":[0.0591365381],"iteration":280,"passed_time":7.303064468,"remaining_time":18.6864888},
{"learn":[0.05881270316],"iteration":281,"passed_time":7.340558837,"remaining_time":18.68979165},
{"learn":[0.05862369045],"iteration":282,"passed_time":7.38049895,"remaining_time":18.69900264},
{"learn":[0.05824178525],"iteration":283,"passed_time":7.417380892,"remaining_time":18.70015746},
{"learn":[0.05806333499],"iteration":284,"passed_time":7.45642629,"remaining_time":18.70647297},
{"learn":[0.05789388259],"iteration":285,"passed_time":7.493215817,"remaining_time":18.70683949},
{"learn":[0.05720588803],"iteration":286,"passed_time":7.53378119,"remaining_time":18.71632749},
{"learn":[0.05692963959],"iteration":287,"passed_time":7.57573905,"remaining_time":18.72891043},
{"learn":[0.05638742083],"iteration":288,"passed_time":7.617002014,"remaining_time":18.73940634},
{"learn":[0.05622261422],"iteration":289,"passed_time":7.659688524,"remaining_time":18.75303052},
{"learn":[0.05606633932],"iteration":290,"passed_time":7.700628648,"remaining_time":18.76201275},
{"learn":[0.05574703815],"iteration":291,"passed_time":7.744479614,"remaining_time":18.77771085},
{"learn":[0.05525144784],"iteration":292,"passed_time":7.791529338,"remaining_time":18.80072096},
{"learn":[0.05510188587],"iteration":293,"passed_time":7.835421159,"remaining_time":18.81567122},
{"learn":[0.0549595904],"iteration":294,"passed_time":7.876407406,"remaining_time":18.82327872},
{"learn":[0.0542851506],"iteration":295,"passed_time":7.920367851,"remaining_time":18.83763165},
{"learn":[0.05400807711],"iteration":296,"passed_time":7.962770316,"remaining_time":18.84790415},
{"learn":[0.05360432781],"iteration":297,"passed_time":8.006508824,"remaining_time":18.86097045},
{"learn":[0.05324492471],"iteration":298,"passed_time":8.051961766,"remaining_time":18.87767625},
{"learn":[0.05259329456],"iteration":299,"passed_time":8.095443993,"remaining_time":18.88936932},
{"learn":[0.05222326742],"iteration":300,"passed_time":8.139617922,"remaining_time":18.90230208},
{"learn":[0.05188711244],"iteration":301,"passed_time":8.187933276,"remaining_time":18.92442857},
{"learn":[0.05176167205],"iteration":302,"passed_time":8.233030702,"remaining_time":18.93868779},
{"learn":[0.05127118055],"iteration":303,"passed_time":8.279322053,"remaining_time":18.95528996},
{"learn":[0.05115163016],"iteration":304,"passed_time":8.321398711,"remaining_time":18.96187575},
{"learn":[0.05072187707],"iteration":305,"passed_time":8.362242359,"remaining_time":18.96534705},
{"learn":[0.05060929524],"iteration":306,"passed_time":8.404392543,"remaining_time":18.97147893},
{"learn":[0.05011038125],"iteration":307,"passed_time":8.446853379,"remaining_time":18.97799525},
{"learn":[0.05000093295],"iteration":308,"passed_time":8.486768887,"remaining_time":18.97850259},
{"learn":[0.04989728152],"iteration":309,"passed_time":8.529601997,"remaining_time":18.98524315},
{"learn":[0.04970021437],"iteration":310,"passed_time":8.571162846,"remaining_time":18.98884631},
{"learn":[0.04909532506],"iteration":311,"passed_time":8.61130856,"remaining_time":18.98903939},
{"learn":[0.04885462317],"iteration":312,"passed_time":8.653267151,"remaining_time":18.99295378},
{"learn":[0.04865646662],"iteration":313,"passed_time":8.701117244,"remaining_time":19.00944723},
{"learn":[0.04847093095],"iteration":314,"passed_time":8.745890601,"remaining_time":19.01884146},
{"learn":[0.0482057321],"iteration":315,"passed_time":8.790554584,"remaining_time":19.02765613},
{"learn":[0.04801872092],"iteration":316,"passed_time":8.831809321,"remaining_time":19.02878791},
{"learn":[0.04763046248],"iteration":317,"passed_time":8.872190327,"remaining_time":19.02777926},
{"learn":[0.0474863889],"iteration":318,"passed_time":8.914276474,"remaining_time":19.03016388},
{"learn":[0.04735026905],"iteration":319,"passed_time":8.967687757,"remaining_time":19.05633648},
{"learn":[0.0471842158],"iteration":320,"passed_time":9.011228345,"remaining_time":19.0611341},
{"learn":[0.04697485954],"iteration":321,"passed_time":9.051187598,"remaining_time":19.05809066},
{"learn":[0.0467672408],"iteration":322,"passed_time":9.092727976,"remaining_time":19.05813263},
{"learn":[0.04659589632],"iteration":323,"passed_time":9.134926444,"remaining_time":19.05929098},
{"learn":[0.0465350131],"iteration":324,"passed_time":9.168996619,"remaining_time":19.04330067},
{"learn":[0.04638023875],"iteration":325,"passed_time":9.208213415,"remaining_time":19.03784001},
{"learn":[0.04618890208],"iteration":326,"passed_time":9.259219164,"remaining_time":19.05643577},
{"learn":[0.04596157881],"iteration":327,"passed_time":9.300243762,"remaining_time":19.05415795},
{"learn":[0.04579325464],"iteration":328,"passed_time":9.340756995,"remaining_time":19.05060165},
{"learn":[0.0456198315],"iteration":329,"passed_time":9.376837386,"remaining_time":19.03782136},
{"learn":[0.04490739548],"iteration":330,"passed_time":9.41227247,"remaining_time":19.02359602},
{"learn":[0.04480324005],"iteration":331,"passed_time":9.451330181,"remaining_time":19.01653181},
{"learn":[0.04464982806],"iteration":332,"passed_time":9.486138855,"remaining_time":19.00076461},
{"learn":[0.04455979404],"iteration":333,"passed_time":9.524024379,"remaining_time":18.99101867},
{"learn":[0.04440101385],"iteration":334,"passed_time":9.561437672,"remaining_time":18.98016732},
{"learn":[0.04371791413],"iteration":335,"passed_time":9.599520383,"remaining_time":18.97048076},
{"learn":[0.04329167912],"iteration":336,"passed_time":9.635509754,"remaining_time":18.95650732},
{"learn":[0.04319284144],"iteration":337,"passed_time":9.670872921,"remaining_time":18.94117714},
{"learn":[0.0431090688],"iteration":338,"passed_time":9.705307461,"remaining_time":18.92391809},
{"learn":[0.04288179528],"iteration":339,"passed_time":9.742728784,"remaining_time":18.91235588},
{"learn":[0.04283200567],"iteration":340,"passed_time":9.773164279,"remaining_time":18.88714152},
{"learn":[0.04272480892],"iteration":341,"passed_time":9.810521221,"remaining_time":18.87521334},
{"learn":[0.0426507713],"iteration":342,"passed_time":9.848259713,"remaining_time":18.86386773},
{"learn":[0.04242389984],"iteration":343,"passed_time":9.886141251,"remaining_time":18.85264146},
{"learn":[0.04220922891],"iteration":344,"passed_time":9.92263845,"remaining_time":18.83863242},
{"learn":[0.04200926795],"iteration":345,"passed_time":9.960513595,"remaining_time":18.82709795},
{"learn":[0.0413551804],"iteration":346,"passed_time":9.999166249,"remaining_time":18.81687481},
{"learn":[0.04116691621],"iteration":347,"passed_time":10.03936006,"remaining_time":18.80937574},
{"learn":[0.04103069587],"iteration":348,"passed_time":10.0778448,"remaining_time":18.79850134},
{"learn":[0.04090246903],"iteration":349,"passed_time":10.11556594,"remaining_time":18.78605104},
{"learn":[0.04027804902],"iteration":350,"passed_time":10.15735437,"remaining_time":18.78097717},
{"learn":[0.04021523916],"iteration":351,"passed_time":10.19249423,"remaining_time":18.76345528},
{"learn":[0.03988950105],"iteration":352,"passed_time":10.22993726,"remaining_time":18.75005498},
{"learn":[0.03959452666],"iteration":353,"passed_time":10.26759215,"remaining_time":18.73690545},
{"learn":[0.03942929205],"iteration":354,"passed_time":10.30670178,"remaining_time":18.72626097},
{"learn":[0.0393899513],"iteration":355,"passed_time":10.33803785,"remaining_time":18.70139431},
{"learn":[0.03911479545],"iteration":356,"passed_time":10.3784638,"remaining_time":18.69286337},
{"learn":[0.03895835726],"iteration":357,"passed_time":10.41770947,"remaining_time":18.68203766},
{"learn":[0.03879470102],"iteration":358,"passed_time":10.45471487,"remaining_time":18.66705357},
{"learn":[0.03815394211],"iteration":359,"passed_time":10.49222456,"remaining_time":18.65284366},
{"learn":[0.0379956975],"iteration":360,"passed_time":10.5315922,"remaining_time":18.6417934},
{"learn":[0.03783458944],"iteration":361,"passed_time":10.57219528,"remaining_time":18.63276406},
{"learn":[0.03765734414],"iteration":362,"passed_time":10.61363165,"remaining_time":18.62502304},
{"learn":[0.03711691836],"iteration":363,"passed_time":10.65095772,"remaining_time":18.60991514},
{"learn":[0.03696126115],"iteration":364,"passed_time":10.68885432,"remaining_time":18.59567806},
{"learn":[0.03679303725],"iteration":365,"passed_time":10.72625544,"remaining_time":18.5804534},
{"learn":[0.03623945548],"iteration":366,"passed_time":10.76405217,"remaining_time":18.56579026},
{"learn":[0.03612891282],"iteration":367,"passed_time":10.80246896,"remaining_time":18.55206627},
{"learn":[0.03559770108],"iteration":368,"passed_time":10.83884736,"remaining_time":18.53472272},
{"learn":[0.03544473608],"iteration":369,"passed_time":10.87629854,"remaining_time":18.51910292},
{"learn":[0.03493548683],"iteration":370,"passed_time":10.91614381,"remaining_time":18.50742441},
{"learn":[0.03471564885],"iteration":371,"passed_time":10.95507208,"remaining_time":18.49404641},
{"learn":[0.03423133275],"iteration":372,"passed_time":10.99323743,"remaining_time":18.47924897},
{"learn":[0.03419979042],"iteration":373,"passed_time":11.02461684,"remaining_time":18.4529683},
{"learn":[0.03373709186],"iteration":374,"passed_time":11.0635098,"remaining_time":18.439183},
{"learn":[0.03362674558],"iteration":375,"passed_time":11.10061142,"remaining_time":18.4222913},
{"learn":[0.03318268613],"iteration":376,"passed_time":11.13784211,"remaining_time":18.40550566},
{"learn":[0.03302501067],"iteration":377,"passed_time":11.16946604,"remaining_time":18.37938592},
{"learn":[0.03282779193],"iteration":378,"passed_time":11.20658984,"remaining_time":18.36224879},
{"learn":[0.03240333295],"iteration":379,"passed_time":11.24210098,"remaining_time":18.34237528},
{"learn":[0.03214844825],"iteration":380,"passed_time":11.27984538,"remaining_time":18.326048},
{"learn":[0.03201148766],"iteration":381,"passed_time":11.31819646,"remaining_time":18.31059009},
{"learn":[0.03177572709],"iteration":382,"passed_time":11.35669646,"remaining_time":18.29525252},
{"learn":[0.03136326031],"iteration":383,"passed_time":11.39262354,"remaining_time":18.27566693},
{"learn":[0.03123635714],"iteration":384,"passed_time":11.43074977,"remaining_time":18.25950937},
{"learn":[0.03101538612],"iteration":385,"passed_time":11.47364179,"remaining_time":18.25081881},
{"learn":[0.03061855422],"iteration":386,"passed_time":11.51536273,"remaining_time":18.24009652},
{"learn":[0.03024099399],"iteration":387,"passed_time":11.55721875,"remaining_time":18.22942751},
{"learn":[0.03002669583],"iteration":388,"passed_time":11.59952455,"remaining_time":18.21930462},
{"learn":[0.02966496161],"iteration":389,"passed_time":11.64455632,"remaining_time":18.21328039},
{"learn":[0.02957586233],"iteration":390,"passed_time":11.67989721,"remaining_time":18.19196266},
{"learn":[0.02923053005],"iteration":391,"passed_time":11.72154857,"remaining_time":18.18036105},
{"learn":[0.02902462923],"iteration":392,"passed_time":11.76298499,"remaining_time":18.16827453},
{"learn":[0.02869261794],"iteration":393,"passed_time":11.80529847,"remaining_time":18.157388},
{"learn":[0.02849567702],"iteration":394,"passed_time":11.84588014,"remaining_time":18.14368983},
{"learn":[0.02838951018],"iteration":395,"passed_time":11.88845025,"remaining_time":18.13288877},
{"learn":[0.02807041223],"iteration":396,"passed_time":11.92907599,"remaining_time":18.11897436},
{"learn":[0.02788589786],"iteration":397,"passed_time":11.97148161,"remaining_time":18.10761792},
{"learn":[0.02758038879],"iteration":398,"passed_time":12.01351407,"remaining_time":18.09554374},
{"learn":[0.027403891],"iteration":399,"passed_time":12.05545139,"remaining_time":18.08317708},
{"learn":[0.02730780683],"iteration":400,"passed_time":12.09666762,"remaining_time":18.0695858},
{"learn":[0.02701419185],"iteration":401,"passed_time":12.14441536,"remaining_time":18.0655731},
{"learn":[0.02684871232],"iteration":402,"passed_time":12.18992027,"remaining_time":18.05802084},
{"learn":[0.02656781737],"iteration":403,"passed_time":12.23534415,"remaining_time":18.05016117},
{"learn":[0.02640954776],"iteration":404,"passed_time":12.27707396,"remaining_time":18.0366889},
{"learn":[0.02632244446],"iteration":405,"passed_time":12.32056312,"remaining_time":18.02565146},
{"learn":[0.02617548747],"iteration":406,"passed_time":12.36186525,"remaining_time":18.01126804},
{"learn":[0.02590355722],"iteration":407,"passed_time":12.40455974,"remaining_time":17.99877295},
{"learn":[0.02576299876],"iteration":408,"passed_time":12.44650172,"remaining_time":17.98504283},
{"learn":[0.0256948248],"iteration":409,"passed_time":12.48082855,"remaining_time":17.96021669},
{"learn":[0.02546598577],"iteration":410,"passed_time":12.52108447,"remaining_time":17.94384125},
{"learn":[0.02525143121],"iteration":411,"passed_time":12.56413681,"remaining_time":17.93134089},
{"learn":[0.02517525587],"iteration":412,"passed_time":12.61016715,"remaining_time":17.92292522},
{"learn":[0.02504237589],"iteration":413,"passed_time":12.65970017,"remaining_time":17.91928575},
{"learn":[0.0248388662],"iteration":414,"passed_time":12.70493793,"remaining_time":17.90937033},
{"learn":[0.02476828683],"iteration":415,"passed_time":12.74986707,"remaining_time":17.89885184},
{"learn":[0.02464316699],"iteration":416,"passed_time":12.79803587,"remaining_time":17.89269762},
{"learn":[0.0244500434],"iteration":417,"passed_time":12.8446113,"remaining_time":17.88412387},
{"learn":[0.02438462889],"iteration":418,"passed_time":12.88905287,"remaining_time":17.87240983},
{"learn":[0.02426675259],"iteration":419,"passed_time":12.9332249,"remaining_time":17.86016772},
{"learn":[0.02408340609],"iteration":420,"passed_time":12.97932171,"remaining_time":17.85042106},
{"learn":[0.02404395231],"iteration":421,"passed_time":13.02399861,"remaining_time":17.83855734},
{"learn":[0.02400749245],"iteration":422,"passed_time":13.06921473,"remaining_time":17.82727399},
{"learn":[0.02397376071],"iteration":423,"passed_time":13.11279899,"remaining_time":17.81361372},
{"learn":[0.0239354445],"iteration":424,"passed_time":13.16036181,"remaining_time":17.80519539},
{"learn":[0.02369599962],"iteration":425,"passed_time":13.20601755,"remaining_time":17.79402365},
{"learn":[0.02365372057],"iteration":426,"passed_time":13.25204832,"remaining_time":17.78319365},
{"learn":[0.02344495659],"iteration":427,"passed_time":13.29840455,"remaining_time":17.77263412},
{"learn":[0.02317004914],"iteration":428,"passed_time":13.34268244,"remaining_time":17.75914143},
{"learn":[0.02312992231],"iteration":429,"passed_time":13.39081845,"remaining_time":17.7506198},
{"learn":[0.02287013967],"iteration":430,"passed_time":13.43665803,"remaining_time":17.73888264},
{"learn":[0.02261760243],"iteration":431,"passed_time":13.47772652,"remaining_time":17.7207145},
{"learn":[0.0223786898],"iteration":432,"passed_time":13.52035641,"remaining_time":17.70448519},
{"learn":[0.02214735032],"iteration":433,"passed_time":13.56029292,"remaining_time":17.68462165},
{"learn":[0.02210789063],"iteration":434,"passed_time":13.60292378,"remaining_time":17.66816537},
{"learn":[0.02186063348],"iteration":435,"passed_time":13.64548788,"remaining_time":17.65150268},
{"learn":[0.02164812889],"iteration":436,"passed_time":13.68623488,"remaining_time":17.63238041},
{"learn":[0.02152712463],"iteration":437,"passed_time":13.72676017,"remaining_time":17.61287493},
{"learn":[0.02132397337],"iteration":438,"passed_time":13.76770153,"remaining_time":17.59380537},
{"learn":[0.02127211701],"iteration":439,"passed_time":13.81288447,"remaining_time":17.58003477},
{"learn":[0.02115850188],"iteration":440,"passed_time":13.85452979,"remaining_time":17.56163753},
{"learn":[0.02096391031],"iteration":441,"passed_time":13.89630831,"remaining_time":17.54330325},
{"learn":[0.02085542011],"iteration":442,"passed_time":13.93810834,"remaining_time":17.52489017},
{"learn":[0.0207774241],"iteration":443,"passed_time":13.97999892,"remaining_time":17.50648513},
{"learn":[0.02074232799],"iteration":444,"passed_time":14.02190852,"remaining_time":17.48799827},
{"learn":[0.02054879789],"iteration":445,"passed_time":14.06443091,"remaining_time":17.47016754},
{"learn":[0.02034058423],"iteration":446,"passed_time":14.10575672,"remaining_time":17.45074601},
{"learn":[0.02014359935],"iteration":447,"passed_time":14.14805916,"remaining_time":17.43243003},
{"learn":[0.01997584035],"iteration":448,"passed_time":14.190697,"remaining_time":17.41441881},
{"learn":[0.01972109402],"iteration":449,"passed_time":14.23303233,"remaining_time":17.3959284},
{"learn":[0.01951899146],"iteration":450,"passed_time":14.27540995,"remaining_time":17.37738373},
{"learn":[0.01940974858],"iteration":451,"passed_time":14.31632613,"remaining_time":17.35696177},
{"learn":[0.01934234777],"iteration":452,"passed_time":14.35613741,"remaining_time":17.33511515},
{"learn":[0.01910907101],"iteration":453,"passed_time":14.39957006,"remaining_time":17.31754461},
{"learn":[0.01892326558],"iteration":454,"passed_time":14.44234475,"remaining_time":17.29907228},
{"learn":[0.01871925512],"iteration":455,"passed_time":14.48332686,"remaining_time":17.27835485},
{"learn":[0.01849951921],"iteration":456,"passed_time":14.52492042,"remaining_time":17.25827524},
{"learn":[0.01839009708],"iteration":457,"passed_time":14.56624592,"remaining_time":17.23778448},
{"learn":[0.01834182593],"iteration":458,"passed_time":14.60890608,"remaining_time":17.21877601},
{"learn":[0.0181338316],"iteration":459,"passed_time":14.64960224,"remaining_time":17.19735915},
{"learn":[0.01785480647],"iteration":460,"passed_time":14.6925242,"remaining_time":17.17846105},
{"learn":[0.01759113812],"iteration":461,"passed_time":14.73472393,"remaining_time":17.15861791},
{"learn":[0.01734197327],"iteration":462,"passed_time":14.77640897,"remaining_time":17.13808125},
{"learn":[0.01710650855],"iteration":463,"passed_time":14.81621724,"remaining_time":17.11528544},
{"learn":[0.01688398692],"iteration":464,"passed_time":14.85944174,"remaining_time":17.09634695},
{"learn":[0.01667369452],"iteration":465,"passed_time":14.89949356,"remaining_time":17.07366859},
{"learn":[0.01647495777],"iteration":466,"passed_time":14.94089532,"remaining_time":17.05245655},
{"learn":[0.01628714079],"iteration":467,"passed_time":14.98148178,"remaining_time":17.03023143},
{"learn":[0.01610964303],"iteration":468,"passed_time":15.0227346,"remaining_time":17.00868246},
{"learn":[0.01594189707],"iteration":469,"passed_time":15.06377488,"remaining_time":16.98680997},
{"learn":[0.01578336668],"iteration":470,"passed_time":15.10480006,"remaining_time":16.96483914},
{"learn":[0.01563354497],"iteration":471,"passed_time":15.14596082,"remaining_time":16.94293922},
{"learn":[0.01552710963],"iteration":472,"passed_time":15.18807646,"remaining_time":16.92202176},
{"learn":[0.01546080149],"iteration":473,"passed_time":15.22976096,"remaining_time":16.90053643},
{"learn":[0.01540933445],"iteration":474,"passed_time":15.27196632,"remaining_time":16.87954173},
{"learn":[0.01527119559],"iteration":475,"passed_time":15.31328143,"remaining_time":16.85747788},
{"learn":[0.01523210097],"iteration":476,"passed_time":15.34803336,"remaining_time":16.8281372},
{"learn":[0.01510144998],"iteration":477,"passed_time":15.38993938,"remaining_time":16.80658652},
{"learn":[0.01497804316],"iteration":478,"passed_time":15.43156376,"remaining_time":16.78464451},
{"learn":[0.01486147402],"iteration":479,"passed_time":15.47396814,"remaining_time":16.76346548},
{"learn":[0.01482395321],"iteration":480,"passed_time":15.50864407,"remaining_time":16.73385919},
{"learn":[0.01471366251],"iteration":481,"passed_time":15.54729298,"remaining_time":16.70850158},
{"learn":[0.01466237961],"iteration":482,"passed_time":15.58867913,"remaining_time":16.68601887},
{"learn":[0.01455783125],"iteration":483,"passed_time":15.62998744,"remaining_time":16.66337504},
{"learn":[0.01445905135],"iteration":484,"passed_time":15.6725312,"remaining_time":16.64196612},
{"learn":[0.01442290076],"iteration":485,"passed_time":15.70723934,"remaining_time":16.61218317},
{"learn":[0.01433590271],"iteration":486,"passed_time":15.7481218,"remaining_time":16.58888394},
{"learn":[0.01430195455],"iteration":487,"passed_time":15.79090121,"remaining_time":16.56750291},
{"learn":[0.01424046119],"iteration":488,"passed_time":15.83132037,"remaining_time":16.54356792},
{"learn":[0.01420720526],"iteration":489,"passed_time":15.86729522,"remaining_time":16.51493992},
{"learn":[0.01411647782],"iteration":490,"passed_time":15.90822077,"remaining_time":16.4914142},
{"learn":[0.01403663677],"iteration":491,"passed_time":15.95165303,"remaining_time":16.47040597},
{"learn":[0.01400546343],"iteration":492,"passed_time":15.9928273,"remaining_time":16.44698466},
{"learn":[0.01394682129],"iteration":493,"passed_time":16.03459091,"remaining_time":16.42409514},
{"learn":[0.01383121183],"iteration":494,"passed_time":16.07656636,"remaining_time":16.40134547},
{"learn":[0.01377756134],"iteration":495,"passed_time":16.13846694,"remaining_time":16.3987648},
{"learn":[0.01367694702],"iteration":496,"passed_time":16.18049952,"remaining_time":16.37583754},
{"learn":[0.01364325757],"iteration":497,"passed_time":16.22254944,"remaining_time":16.35285104},
{"learn":[0.01355864997],"iteration":498,"passed_time":16.26359133,"remaining_time":16.32877606},
{"learn":[0.01348412251],"iteration":499,"passed_time":16.30467714,"remaining_time":16.30467714},
{"learn":[0.01345195261],"iteration":500,"passed_time":16.3453607,"remaining_time":16.28010976},
{"learn":[0.01338104352],"iteration":501,"passed_time":16.39491646,"remaining_time":16.26427968},
{"learn":[0.01335046126],"iteration":502,"passed_time":16.43884775,"remaining_time":16.24275811},
{"learn":[0.01332157642],"iteration":503,"passed_time":16.48368378,"remaining_time":16.22203801},
{"learn":[0.01324695163],"iteration":504,"passed_time":16.5264987,"remaining_time":16.1992413},
{"learn":[0.0131819085],"iteration":505,"passed_time":16.56900804,"remaining_time":16.17606714},
{"learn":[0.01315315943],"iteration":506,"passed_time":16.61043716,"remaining_time":16.15176631},
{"learn":[0.01312583851],"iteration":507,"passed_time":16.65071297,"remaining_time":16.12628107},
{"learn":[0.01302610886],"iteration":508,"passed_time":16.69118077,"remaining_time":16.10092291},
{"learn":[0.0129226055],"iteration":509,"passed_time":16.73297883,"remaining_time":16.07678359},
{"learn":[0.01283167794],"iteration":510,"passed_time":16.77652109,"remaining_time":16.05424426},
{"learn":[0.01276463589],"iteration":511,"passed_time":16.81794503,"remaining_time":16.02960386},
{"learn":[0.01273845802],"iteration":512,"passed_time":16.85902478,"remaining_time":16.00457128},
{"learn":[0.01267475737],"iteration":513,"passed_time":16.91007041,"remaining_time":15.98889926},
{"learn":[0.01264985031],"iteration":514,"passed_time":16.95895444,"remaining_time":15.97105418},
{"learn":[0.01258198025],"iteration":515,"passed_time":17.00353639,"remaining_time":15.94905351},
{"learn":[0.01255836101],"iteration":516,"passed_time":17.0470571,"remaining_time":15.92597404},
{"learn":[0.01249992913],"iteration":517,"passed_time":17.09134608,"remaining_time":15.90353052},
{"learn":[0.01247594257],"iteration":518,"passed_time":17.13686813,"remaining_time":15.8821456},
{"learn":[0.01238218508],"iteration":519,"passed_time":17.18468113,"remaining_time":15.86278258},
{"learn":[0.01232632388],"iteration":520,"passed_time":17.22822633,"remaining_time":15.83938659},
{"learn":[0.01230335444],"iteration":521,"passed_time":17.27431308,"remaining_time":15.81824071},
{"learn":[0.01228151123],"iteration":522,"passed_time":17.31789708,"remaining_time":15.79471684},
{"learn":[0.01221876113],"iteration":523,"passed_time":17.36342124,"remaining_time":15.77287883},
{"learn":[0.01215884451],"iteration":524,"passed_time":17.40784989,"remaining_time":15.74995942},
{"learn":[0.01213802444],"iteration":525,"passed_time":17.45349,"remaining_time":15.72804992},
{"learn":[0.01205315805],"iteration":526,"passed_time":17.49844012,"remaining_time":15.70543107},
{"learn":[0.01199907573],"iteration":527,"passed_time":17.54177903,"remaining_time":15.68128731},
{"learn":[0.01194664193],"iteration":528,"passed_time":17.58675323,"remaining_time":15.65852698},
{"learn":[0.01192731936],"iteration":529,"passed_time":17.63246772,"remaining_time":15.6363393},
{"learn":[0.01187556163],"iteration":530,"passed_time":17.67864743,"remaining_time":15.61447391},
{"learn":[0.01182744964],"iteration":531,"passed_time":17.72393773,"remaining_time":15.59173469},
{"learn":[0.01164942015],"iteration":532,"passed_time":17.76544804,"remaining_time":15.56559894},
{"learn":[0.01160442015],"iteration":533,"passed_time":17.81118727,"remaining_time":15.54309601},
{"learn":[0.01156288172],"iteration":534,"passed_time":17.85252408,"remaining_time":15.5166798},
{"learn":[0.01144400566],"iteration":535,"passed_time":17.89502219,"remaining_time":15.49121324},
{"learn":[0.01142688185],"iteration":536,"passed_time":17.93627218,"remaining_time":15.46460711},
{"learn":[0.01131379518],"iteration":537,"passed_time":17.97701508,"remaining_time":15.43751109},
{"learn":[0.0112973673],"iteration":538,"passed_time":18.01696574,"remaining_time":15.40968684},
{"learn":[0.01128173578],"iteration":539,"passed_time":18.05839517,"remaining_time":15.38307737},
{"learn":[0.01117398665],"iteration":540,"passed_time":18.09900939,"remaining_time":15.35572146},
{"learn":[0.01103765955],"iteration":541,"passed_time":18.13926778,"remaining_time":15.32801594},
{"learn":[0.01090895971],"iteration":542,"passed_time":18.18629333,"remaining_time":15.30595958},
{"learn":[0.010868694],"iteration":543,"passed_time":18.22686567,"remaining_time":15.27840211},
{"learn":[0.01076480047],"iteration":544,"passed_time":18.26766104,"remaining_time":15.25098307},
{"learn":[0.01064232788],"iteration":545,"passed_time":18.30890472,"remaining_time":15.22388781},
{"learn":[0.01060313197],"iteration":546,"passed_time":18.35110706,"remaining_time":15.19753473},
{"learn":[0.01050337944],"iteration":547,"passed_time":18.3916563,"remaining_time":15.1697603},
{"learn":[0.01038677865],"iteration":548,"passed_time":18.43430318,"remaining_time":15.14366254},
{"learn":[0.01034864176],"iteration":549,"passed_time":18.47582403,"remaining_time":15.11658329},
{"learn":[0.01027659012],"iteration":550,"passed_time":18.51661287,"remaining_time":15.08885514},
{"learn":[0.01018074587],"iteration":551,"passed_time":18.55948469,"remaining_time":15.06277019},
{"learn":[0.01006886465],"iteration":552,"passed_time":18.60100036,"remaining_time":15.03552832},
{"learn":[0.01003307165],"iteration":553,"passed_time":18.64222579,"remaining_time":15.00800127},
{"learn":[0.009966219149],"iteration":554,"passed_time":18.68446718,"remaining_time":14.98123945},
{"learn":[0.009875579943],"iteration":555,"passed_time":18.72636684,"remaining_time":14.95414906},
{"learn":[0.009760458554],"iteration":556,"passed_time":18.7722772,"remaining_time":14.93019533},
{"learn":[0.009726871754],"iteration":557,"passed_time":18.81367293,"remaining_time":14.9025868},
{"learn":[0.009640523209],"iteration":558,"passed_time":18.85532845,"remaining_time":14.87513389},
{"learn":[0.009596241001],"iteration":559,"passed_time":18.89671721,"remaining_time":14.84742066},
{"learn":[0.009490775187],"iteration":560,"passed_time":18.93779124,"remaining_time":14.8194124},
{"learn":[0.009429005203],"iteration":561,"passed_time":18.98726111,"remaining_time":14.797901},
{"learn":[0.009397288966],"iteration":562,"passed_time":19.02909108,"remaining_time":14.77036022},
{"learn":[0.009339342056],"iteration":563,"passed_time":19.07009794,"remaining_time":14.74213245},
{"learn":[0.009260835585],"iteration":564,"passed_time":19.11075721,"remaining_time":14.71359184},
{"learn":[0.009217298163],"iteration":565,"passed_time":19.15133874,"remaining_time":14.68494878},
{"learn":[0.009203632336],"iteration":566,"passed_time":19.19197284,"remaining_time":14.65630378},
{"learn":[0.009128741063],"iteration":567,"passed_time":19.23364954,"remaining_time":14.62840951},
{"learn":[0.009030929084],"iteration":568,"passed_time":19.27564028,"remaining_time":14.60070468},
{"learn":[0.009017693796],"iteration":569,"passed_time":19.31650932,"remaining_time":14.57210352},
{"learn":[0.008916604537],"iteration":570,"passed_time":19.35748519,"remaining_time":14.54353966},
{"learn":[0.008886501496],"iteration":571,"passed_time":19.39992366,"remaining_time":14.51602679},
{"learn":[0.008839913908],"iteration":572,"passed_time":19.44224632,"remaining_time":14.48837553},
{"learn":[0.008828303664],"iteration":573,"passed_time":19.48422606,"remaining_time":14.46041864},
{"learn":[0.008799713381],"iteration":574,"passed_time":19.52646555,"remaining_time":14.43260497},
{"learn":[0.008709011467],"iteration":575,"passed_time":19.56684093,"remaining_time":14.40336902},
{"learn":[0.008656587872],"iteration":576,"passed_time":19.6065359,"remaining_time":14.37359564},
{"learn":[0.00862996435],"iteration":577,"passed_time":19.64795063,"remaining_time":14.34504354},
{"learn":[0.008587123916],"iteration":578,"passed_time":19.68986969,"remaining_time":14.31681372},
{"learn":[0.00857042206],"iteration":579,"passed_time":19.73033602,"remaining_time":14.28748471},
{"learn":[0.008529318977],"iteration":580,"passed_time":19.77079358,"remaining_time":14.25811103},
{"learn":[0.008489204888],"iteration":581,"passed_time":19.81209251,"remaining_time":14.22930356},
{"learn":[0.008402446853],"iteration":582,"passed_time":19.85185298,"remaining_time":14.19935282},
{"learn":[0.008366393397],"iteration":583,"passed_time":19.91884166,"remaining_time":14.18876392},
{"learn":[0.008283250557],"iteration":584,"passed_time":19.96063733,"remaining_time":14.16011024},
{"learn":[0.008245697732],"iteration":585,"passed_time":20.00308956,"remaining_time":14.13187556},
{"learn":[0.008166935996],"iteration":586,"passed_time":20.04266631,"remaining_time":14.10156931},
{"learn":[0.008141500889],"iteration":587,"passed_time":20.0836218,"remaining_time":14.07219759},
{"learn":[0.00812657706],"iteration":588,"passed_time":20.1243649,"remaining_time":14.04263832},
{"learn":[0.008092747079],"iteration":589,"passed_time":20.16505735,"remaining_time":14.01300595},
{"learn":[0.008017046481],"iteration":590,"passed_time":20.20729354,"remaining_time":13.9844045},
{"learn":[0.008002847121],"iteration":591,"passed_time":20.24723966,"remaining_time":13.95417868},
{"learn":[0.007970714035],"iteration":592,"passed_time":20.28777167,"remaining_time":13.92432221},
{"learn":[0.007882895326],"iteration":593,"passed_time":20.33045622,"remaining_time":13.89590105},
{"learn":[0.007811533827],"iteration":594,"passed_time":20.3712849,"remaining_time":13.86616871},
{"learn":[0.007797791321],"iteration":595,"passed_time":20.41352582,"remaining_time":13.83735643},
{"learn":[0.007762827493],"iteration":596,"passed_time":20.45618811,"remaining_time":13.8087836},
{"learn":[0.007679814442],"iteration":597,"passed_time":20.49811744,"remaining_time":13.77967092},
{"learn":[0.007612850207],"iteration":598,"passed_time":20.54048174,"remaining_time":13.75080664},
{"learn":[0.007589540859],"iteration":599,"passed_time":20.58095418,"remaining_time":13.72063612},
{"learn":[0.007556316742],"iteration":600,"passed_time":20.62390721,"remaining_time":13.69207817},
{"learn":[0.007525616595],"iteration":601,"passed_time":20.6744016,"remaining_time":13.6684582},
{"learn":[0.00742165452],"iteration":602,"passed_time":20.72022388,"remaining_time":13.6416731},
{"learn":[0.007389894486],"iteration":603,"passed_time":20.76370856,"remaining_time":13.61329237},
{"learn":[0.007290884976],"iteration":604,"passed_time":20.80553345,"remaining_time":13.58377804},
{"learn":[0.007272350214],"iteration":605,"passed_time":20.84914494,"remaining_time":13.55538467},
{"learn":[0.007192628771],"iteration":606,"passed_time":20.89024546,"remaining_time":13.52531543},
{"learn":[0.007163027971],"iteration":607,"passed_time":20.93178231,"remaining_time":13.49549122},
{"learn":[0.007086800187],"iteration":608,"passed_time":20.97273755,"remaining_time":13.46525514},
{"learn":[0.007055830396],"iteration":609,"passed_time":21.01496706,"remaining_time":13.43579861},
{"learn":[0.007034275716],"iteration":610,"passed_time":21.05573021,"remaining_time":13.4053667},
{"learn":[0.006961199862],"iteration":611,"passed_time":21.09742784,"remaining_time":13.37549347},
{"learn":[0.006940515914],"iteration":612,"passed_time":21.13864324,"remaining_time":13.34527722},
{"learn":[0.006920851239],"iteration":613,"passed_time":21.18268172,"remaining_time":13.31679991},
{"learn":[0.006875534366],"iteration":614,"passed_time":21.22712805,"remaining_time":13.28852732},
{"learn":[0.00686385774],"iteration":615,"passed_time":21.27260207,"remaining_time":13.26084285},
{"learn":[0.006852811255],"iteration":616,"passed_time":21.31840075,"remaining_time":13.23330225},
{"learn":[0.006809643995],"iteration":617,"passed_time":21.36325079,"remaining_time":13.20511618},
{"learn":[0.006723153305],"iteration":618,"passed_time":21.40991454,"remaining_time":13.17799263},
{"learn":[0.006712539165],"iteration":619,"passed_time":21.45414986,"remaining_time":13.14931766},
{"learn":[0.006672258105],"iteration":620,"passed_time":21.49950898,"remaining_time":13.12127843},
{"learn":[0.006632164541],"iteration":621,"passed_time":21.54436023,"remaining_time":13.09287486},
{"learn":[0.006602823669],"iteration":622,"passed_time":21.59010039,"remaining_time":13.06495642},
{"learn":[0.006573828897],"iteration":623,"passed_time":21.63705901,"remaining_time":13.03771505},
{"learn":[0.0065593096],"iteration":624,"passed_time":21.68423596,"remaining_time":13.01054157},
{"learn":[0.006501230038],"iteration":625,"passed_time":21.72929995,"remaining_time":12.98204182},
{"learn":[0.006473595874],"iteration":626,"passed_time":21.77314371,"remaining_time":12.95276332},
{"learn":[0.006439183338],"iteration":627,"passed_time":21.81704752,"remaining_time":12.92347401},
{"learn":[0.006381447787],"iteration":628,"passed_time":21.85595916,"remaining_time":12.89119372},
{"learn":[0.006299914852],"iteration":629,"passed_time":21.8974478,"remaining_time":12.86040585},
{"learn":[0.00627326143],"iteration":630,"passed_time":21.9371661,"remaining_time":12.8285488},
{"learn":[0.006195621055],"iteration":631,"passed_time":21.9839462,"remaining_time":12.8007788},
{"learn":[0.006121993444],"iteration":632,"passed_time":22.0193175,"remaining_time":12.76633416},
{"learn":[0.006107694679],"iteration":633,"passed_time":22.05395447,"remaining_time":12.73146267},
{"learn":[0.006048283709],"iteration":634,"passed_time":22.09041309,"remaining_time":12.69763902},
{"learn":[0.006022411551],"iteration":635,"passed_time":22.12736978,"remaining_time":12.66409214},
{"learn":[0.005965607589],"iteration":636,"passed_time":22.16150991,"remaining_time":12.62892951},
{"learn":[0.00592731778],"iteration":637,"passed_time":22.19859039,"remaining_time":12.59543843},
{"learn":[0.005913727022],"iteration":638,"passed_time":22.23522407,"remaining_time":12.56168371},
{"learn":[0.005856231672],"iteration":639,"passed_time":22.27312381,"remaining_time":12.52863215},
{"learn":[0.005801720591],"iteration":640,"passed_time":22.3090326,"remaining_time":12.49445039},
{"learn":[0.005764945756],"iteration":641,"passed_time":22.34612781,"remaining_time":12.46092485},
{"learn":[0.005751852241],"iteration":642,"passed_time":22.38240553,"remaining_time":12.42693433},
{"learn":[0.005702061084],"iteration":643,"passed_time":22.42087125,"remaining_time":12.39414622},
{"learn":[0.005675630976],"iteration":644,"passed_time":22.45935427,"remaining_time":12.36135003},
{"learn":[0.005663053456],"iteration":645,"passed_time":22.49464126,"remaining_time":12.32678484},
{"learn":[0.005612920727],"iteration":646,"passed_time":22.53227075,"remaining_time":12.29349548},
{"learn":[0.005587517761],"iteration":647,"passed_time":22.56940209,"remaining_time":12.25992212},
{"learn":[0.005565238339],"iteration":648,"passed_time":22.60804219,"remaining_time":12.22715379},
{"learn":[0.005519441489],"iteration":649,"passed_time":22.6464562,"remaining_time":12.19424565},
{"learn":[0.005476357838],"iteration":650,"passed_time":22.68935001,"remaining_time":12.1637222},
{"learn":[0.005455149656],"iteration":651,"passed_time":22.73101654,"remaining_time":12.13250576},
{"learn":[0.005408879865],"iteration":652,"passed_time":22.77202044,"remaining_time":12.10090519},
{"learn":[0.005363647471],"iteration":653,"passed_time":22.81307363,"remaining_time":12.06930195},
{"learn":[0.005349104141],"iteration":654,"passed_time":22.85966059,"remaining_time":12.04058458},
{"learn":[0.005317674849],"iteration":655,"passed_time":22.90131344,"remaining_time":12.00922534},
{"learn":[0.005306654034],"iteration":656,"passed_time":22.94301782,"remaining_time":11.97786166},
{"learn":[0.005296188583],"iteration":657,"passed_time":22.9849546,"remaining_time":11.94658734},
{"learn":[0.005244213531],"iteration":658,"passed_time":23.02611733,"remaining_time":11.91488013},
{"learn":[0.005200571214],"iteration":659,"passed_time":23.0676654,"remaining_time":11.88334278},
{"learn":[0.005161766737],"iteration":660,"passed_time":23.10936622,"remaining_time":11.85185348},
{"learn":[0.005137479734],"iteration":661,"passed_time":23.14921569,"remaining_time":11.81938807},
{"learn":[0.005118432526],"iteration":662,"passed_time":23.19131034,"remaining_time":11.78804161},
{"learn":[0.005089584632],"iteration":663,"passed_time":23.23176765,"remaining_time":11.75583423},
{"learn":[0.005052137357],"iteration":664,"passed_time":23.27415302,"remaining_time":11.72457333},
{"learn":[0.00503456511],"iteration":665,"passed_time":23.31659973,"remaining_time":11.69330977},
{"learn":[0.004990058686],"iteration":666,"passed_time":23.35698984,"remaining_time":11.66098593},
{"learn":[0.004949994466],"iteration":667,"passed_time":23.40052155,"remaining_time":11.63019933},
{"learn":[0.00492224246],"iteration":668,"passed_time":23.44234945,"remaining_time":11.59853164},
{"learn":[0.00491302486],"iteration":669,"passed_time":23.48547639,"remaining_time":11.56747345},
{"learn":[0.004878152988],"iteration":670,"passed_time":23.5259641,"remaining_time":11.53508523},
{"learn":[0.004861802937],"iteration":671,"passed_time":23.56838859,"remaining_time":11.50361824},
{"learn":[0.004834431156],"iteration":672,"passed_time":23.60958688,"remaining_time":11.4715229},
{"learn":[0.004790962382],"iteration":673,"passed_time":23.65156999,"remaining_time":11.43978014},
{"learn":[0.004782617479],"iteration":674,"passed_time":23.69227295,"remaining_time":11.40739068},
{"learn":[0.00474459852],"iteration":675,"passed_time":23.73312084,"remaining_time":11.37504608},
{"learn":[0.004718352009],"iteration":676,"passed_time":23.77502458,"remaining_time":11.34318012},
{"learn":[0.004710509518],"iteration":677,"passed_time":23.81626809,"remaining_time":11.31097098},
{"learn":[0.004668586135],"iteration":678,"passed_time":23.85637335,"remaining_time":11.27819712},
{"learn":[0.00463563365],"iteration":679,"passed_time":23.89706257,"remaining_time":11.24567651},
{"learn":[0.004599987811],"iteration":680,"passed_time":23.93917579,"remaining_time":11.21379894},
{"learn":[0.004584997894],"iteration":681,"passed_time":23.97911763,"remaining_time":11.1808789},
{"learn":[0.004559883933],"iteration":682,"passed_time":24.02075643,"remaining_time":11.1487259},
{"learn":[0.004513271485],"iteration":683,"passed_time":24.06133703,"remaining_time":11.11605629},
{"learn":[0.004478883237],"iteration":684,"passed_time":24.10390962,"remaining_time":11.08427961},
{"learn":[0.004446134725],"iteration":685,"passed_time":24.14576201,"remaining_time":11.05214179},
{"learn":[0.004422615678],"iteration":686,"passed_time":24.18643789,"remaining_time":11.01943968},
{"learn":[0.004415497653],"iteration":687,"passed_time":24.22703535,"remaining_time":10.98667882},
{"learn":[0.004373459434],"iteration":688,"passed_time":24.26897527,"remaining_time":10.95450117},
{"learn":[0.00434102357],"iteration":689,"passed_time":24.3137362,"remaining_time":10.92356264},
{"learn":[0.004327166784],"iteration":690,"passed_time":24.35427041,"remaining_time":10.89069401},
{"learn":[0.004308445412],"iteration":691,"passed_time":24.40377278,"remaining_time":10.86179482},
{"learn":[0.004269725037],"iteration":692,"passed_time":24.44581607,"remaining_time":10.82953179},
{"learn":[0.004262868118],"iteration":693,"passed_time":24.48729152,"remaining_time":10.79699021},
{"learn":[0.004224020233],"iteration":694,"passed_time":24.52798415,"remaining_time":10.76407938},
{"learn":[0.004176852401],"iteration":695,"passed_time":24.57170973,"remaining_time":10.73247092},
{"learn":[0.004158559332],"iteration":696,"passed_time":24.61257284,"remaining_time":10.69958331},
{"learn":[0.004122975582],"iteration":697,"passed_time":24.65456109,"remaining_time":10.66715967},
{"learn":[0.004103361939],"iteration":698,"passed_time":24.69516705,"remaining_time":10.63411342},
{"learn":[0.004081792128],"iteration":699,"passed_time":24.73590498,"remaining_time":10.60110214},
{"learn":[0.004054872508],"iteration":700,"passed_time":24.77629909,"remaining_time":10.56792215},
{"learn":[0.004036940761],"iteration":701,"passed_time":24.82678578,"remaining_time":10.53900593},
{"learn":[0.00401145283],"iteration":702,"passed_time":24.87210803,"remaining_time":10.50784649},
{"learn":[0.003986235843],"iteration":703,"passed_time":24.91758153,"remaining_time":10.47671042},
{"learn":[0.003962701734],"iteration":704,"passed_time":24.96014095,"remaining_time":10.4443143},
{"learn":[0.003954511985],"iteration":705,"passed_time":25.0006238,"remaining_time":10.41102464},
{"learn":[0.003931962392],"iteration":706,"passed_time":25.04131159,"remaining_time":10.37779957},
{"learn":[0.003908237484],"iteration":707,"passed_time":25.08127563,"remaining_time":10.34425492},
{"learn":[0.003886284781],"iteration":708,"passed_time":25.122131,"remaining_time":10.311058},
{"learn":[0.00386554003],"iteration":709,"passed_time":25.16481336,"remaining_time":10.27858574},
{"learn":[0.003843723672],"iteration":710,"passed_time":25.20776375,"remaining_time":10.24619371},
{"learn":[0.003821866665],"iteration":711,"passed_time":25.2477672,"remaining_time":10.21257999},
{"learn":[0.003814029044],"iteration":712,"passed_time":25.28918999,"remaining_time":10.17951967},
{"learn":[0.003794643714],"iteration":713,"passed_time":25.33785505,"remaining_time":10.1493369},
{"learn":[0.003774168499],"iteration":714,"passed_time":25.38464199,"remaining_time":10.1183538},
{"learn":[0.003753364326],"iteration":715,"passed_time":25.42671433,"remaining_time":10.08545652},
{"learn":[0.003735284563],"iteration":716,"passed_time":25.46824654,"remaining_time":10.05232046},
{"learn":[0.003716933314],"iteration":717,"passed_time":25.50668322,"remaining_time":10.01794522},
{"learn":[0.003709586863],"iteration":718,"passed_time":25.54778949,"remaining_time":9.984602013},
{"learn":[0.003665812482],"iteration":719,"passed_time":25.58869595,"remaining_time":9.951159536},
{"learn":[0.003645689684],"iteration":720,"passed_time":25.63077286,"remaining_time":9.918149276},
{"learn":[0.003625665149],"iteration":721,"passed_time":25.67321858,"remaining_time":9.885255908},
{"learn":[0.00361880476],"iteration":722,"passed_time":25.71375327,"remaining_time":9.851603948},
{"learn":[0.003576918718],"iteration":723,"passed_time":25.75433293,"remaining_time":9.817950122},
{"learn":[0.003559472193],"iteration":724,"passed_time":25.79588271,"remaining_time":9.784645165},
{"learn":[0.003552846652],"iteration":725,"passed_time":25.84037335,"remaining_time":9.752427409},
{"learn":[0.003530402957],"iteration":726,"passed_time":25.88098962,"remaining_time":9.718720999},
{"learn":[0.003490346224],"iteration":727,"passed_time":25.92163367,"remaining_time":9.685005985},
{"learn":[0.00347108443],"iteration":728,"passed_time":25.96331411,"remaining_time":9.651657234},
{"learn":[0.003450931864],"iteration":729,"passed_time":26.01055606,"remaining_time":9.620342651},
{"learn":[0.003433569846],"iteration":730,"passed_time":26.05143932,"remaining_time":9.586644566},
{"learn":[0.003394882406],"iteration":731,"passed_time":26.09185942,"remaining_time":9.552757272},
{"learn":[0.003363943741],"iteration":732,"passed_time":26.1320871,"remaining_time":9.518782066},
{"learn":[0.003334174244],"iteration":733,"passed_time":26.17074623,"remaining_time":9.484221387},
{"learn":[0.00333122031],"iteration":734,"passed_time":26.21559581,"remaining_time":9.451881483},
{"learn":[0.003302993009],"iteration":735,"passed_time":26.25263685,"remaining_time":9.416706696},
{"learn":[0.003300172011],"iteration":736,"passed_time":26.29317988,"remaining_time":9.382776538},
{"learn":[0.003254027668],"iteration":737,"passed_time":26.33453776,"remaining_time":9.349117741},
{"learn":[0.003228252226],"iteration":738,"passed_time":26.37589928,"remaining_time":9.315439395},
{"learn":[0.003203665837],"iteration":739,"passed_time":26.41645573,"remaining_time":9.281457417},
{"learn":[0.003186993559],"iteration":740,"passed_time":26.45716493,"remaining_time":9.247511089},
{"learn":[0.003163417485],"iteration":741,"passed_time":26.4982732,"remaining_time":9.21368529},
{"learn":[0.003140928417],"iteration":742,"passed_time":26.53868074,"remaining_time":9.17959751},
{"learn":[0.00311458392],"iteration":743,"passed_time":26.57871864,"remaining_time":9.145365553},
{"learn":[0.003098593888],"iteration":744,"passed_time":26.62040474,"remaining_time":9.111682161},
{"learn":[0.003072709413],"iteration":745,"passed_time":26.66175563,"remaining_time":9.077863177},
{"learn":[0.003048713649],"iteration":746,"passed_time":26.70268179,"remaining_time":9.043880179},
{"learn":[0.003025991804],"iteration":747,"passed_time":26.74409729,"remaining_time":9.010043471},
{"learn":[0.00300321373],"iteration":748,"passed_time":26.78491073,"remaining_time":8.975984771},
{"learn":[0.00298120117],"iteration":749,"passed_time":26.82718975,"remaining_time":8.942396583},
{"learn":[0.002960366848],"iteration":750,"passed_time":26.86748014,"remaining_time":8.908125905},
{"learn":[0.002953831081],"iteration":751,"passed_time":26.90943333,"remaining_time":8.874387589},
{"learn":[0.00293269629],"iteration":752,"passed_time":26.95048396,"remaining_time":8.840331393},
{"learn":[0.002907524456],"iteration":753,"passed_time":26.99134598,"remaining_time":8.806195109},
{"learn":[0.00287339966],"iteration":754,"passed_time":27.03254827,"remaining_time":8.772151426},
{"learn":[0.00285692999],"iteration":755,"passed_time":27.07159967,"remaining_time":8.737394602},
{"learn":[0.002850776765],"iteration":756,"passed_time":27.11184419,"remaining_time":8.70300943},
{"learn":[0.002802067106],"iteration":757,"passed_time":27.15403134,"remaining_time":8.669229003},
{"learn":[0.002786429997],"iteration":758,"passed_time":27.19502821,"remaining_time":8.635048482},
{"learn":[0.002783976648],"iteration":759,"passed_time":27.2382248,"remaining_time":8.601544674},
{"learn":[0.00276913957],"iteration":760,"passed_time":27.27997705,"remaining_time":8.56756178},
{"learn":[0.002766640616],"iteration":761,"passed_time":27.32090439,"remaining_time":8.533300848},
{"learn":[0.002745038614],"iteration":762,"passed_time":27.36202858,"remaining_time":8.499083581},
{"learn":[0.002723701599],"iteration":763,"passed_time":27.40519055,"remaining_time":8.465477709},
{"learn":[0.002704004933],"iteration":764,"passed_time":27.44620516,"remaining_time":8.431187205},
{"learn":[0.002681628592],"iteration":765,"passed_time":27.48603335,"remaining_time":8.396516715},
{"learn":[0.002637179736],"iteration":766,"passed_time":27.52778467,"remaining_time":8.362416987},
{"learn":[0.002634825391],"iteration":767,"passed_time":27.56967909,"remaining_time":8.32834056},
{"learn":[0.002610697399],"iteration":768,"passed_time":27.61670388,"remaining_time":8.295784911},
{"learn":[0.002596649718],"iteration":769,"passed_time":27.65770418,"remaining_time":8.261392157},
{"learn":[0.002584542878],"iteration":770,"passed_time":27.69850587,"remaining_time":8.226923274},
{"learn":[0.002561444201],"iteration":771,"passed_time":27.73930937,"remaining_time":8.192438518},
{"learn":[0.002559213193],"iteration":772,"passed_time":27.7811312,"remaining_time":8.158236458},
{"learn":[0.002518405111],"iteration":773,"passed_time":27.82413577,"remaining_time":8.124360057},
{"learn":[0.00249669244],"iteration":774,"passed_time":27.86599349,"remaining_time":8.090127142},
{"learn":[0.002483453972],"iteration":775,"passed_time":27.90839927,"remaining_time":8.056032778},
{"learn":[0.002462756437],"iteration":776,"passed_time":27.94841889,"remaining_time":8.021232191},
{"learn":[0.002460571543],"iteration":777,"passed_time":27.99059883,"remaining_time":7.987034627},
{"learn":[0.002436025689],"iteration":778,"passed_time":28.03284057,"remaining_time":7.952834101},
{"learn":[0.002423177613],"iteration":779,"passed_time":28.07577901,"remaining_time":7.918809465},
{"learn":[0.002385736184],"iteration":780,"passed_time":28.11669174,"remaining_time":7.884193971},
{"learn":[0.002379564263],"iteration":781,"passed_time":28.15797212,"remaining_time":7.849664861},
{"learn":[0.002360485573],"iteration":782,"passed_time":28.19971133,"remaining_time":7.815245668},
{"learn":[0.002342392434],"iteration":783,"passed_time":28.24506854,"remaining_time":7.781804598},
{"learn":[0.002329866121],"iteration":784,"passed_time":28.28533843,"remaining_time":7.746939824},
{"learn":[0.002310745323],"iteration":785,"passed_time":28.3307026,"remaining_time":7.71344829},
{"learn":[0.00229874123],"iteration":786,"passed_time":28.37137875,"remaining_time":7.678657782},
{"learn":[0.002281267161],"iteration":787,"passed_time":28.41143206,"remaining_time":7.643684766},
{"learn":[0.00226981658],"iteration":788,"passed_time":28.45174939,"remaining_time":7.608769483},
{"learn":[0.002259677071],"iteration":789,"passed_time":28.49477766,"remaining_time":7.57456115},
{"learn":[0.002241029687],"iteration":790,"passed_time":28.53577163,"remaining_time":7.539793009},
{"learn":[0.00222888379],"iteration":791,"passed_time":28.57544358,"remaining_time":7.504661951},
{"learn":[0.002217431315],"iteration":792,"passed_time":28.62688581,"remaining_time":7.472591883},
{"learn":[0.002197152569],"iteration":793,"passed_time":28.66948371,"remaining_time":7.438178392},
{"learn":[0.002186219132],"iteration":794,"passed_time":28.70952958,"remaining_time":7.403086245},
{"learn":[0.002175904612],"iteration":795,"passed_time":28.74961553,"remaining_time":7.367991919},
{"learn":[0.002156300832],"iteration":796,"passed_time":28.79227663,"remaining_time":7.333540974},
{"learn":[0.002146448006],"iteration":797,"passed_time":28.83342975,"remaining_time":7.298687732},
{"learn":[0.00212062244],"iteration":798,"passed_time":28.87554686,"remaining_time":7.264061225},
{"learn":[0.002111270021],"iteration":799,"passed_time":28.91479402,"remaining_time":7.228698506},
{"learn":[0.00208964432],"iteration":800,"passed_time":28.95495893,"remaining_time":7.193554092},
{"learn":[0.00207491207],"iteration":801,"passed_time":29.00047256,"remaining_time":7.159717663},
{"learn":[0.002066410536],"iteration":802,"passed_time":29.04455938,"remaining_time":7.125502114},
{"learn":[0.002058030022],"iteration":803,"passed_time":29.08938052,"remaining_time":7.091441023},
{"learn":[0.002039408071],"iteration":804,"passed_time":29.13164641,"remaining_time":7.056734224},
{"learn":[0.002014721686],"iteration":805,"passed_time":29.17165235,"remaining_time":7.021464709},
{"learn":[0.00200077926],"iteration":806,"passed_time":29.21797822,"remaining_time":6.987694915},
{"learn":[0.001982970706],"iteration":807,"passed_time":29.26115494,"remaining_time":6.953145728},
{"learn":[0.001966257072],"iteration":808,"passed_time":29.30151244,"remaining_time":6.917909611},
{"learn":[0.001950456283],"iteration":809,"passed_time":29.35012479,"remaining_time":6.884597173},
{"learn":[0.00194208995],"iteration":810,"passed_time":29.39012945,"remaining_time":6.849241019},
{"learn":[0.001925226837],"iteration":811,"passed_time":29.43224586,"remaining_time":6.814362343},
{"learn":[0.00191024925],"iteration":812,"passed_time":29.47286514,"remaining_time":6.779121502},
{"learn":[0.001896086437],"iteration":813,"passed_time":29.51900427,"remaining_time":6.745128739},
{"learn":[0.00188014187],"iteration":814,"passed_time":29.56261145,"remaining_time":6.710531434},
{"learn":[0.001868129947],"iteration":815,"passed_time":29.60517521,"remaining_time":6.675676764},
{"learn":[0.001855366387],"iteration":816,"passed_time":29.64926812,"remaining_time":6.641145736},
{"learn":[0.00184031115],"iteration":817,"passed_time":29.69317087,"remaining_time":6.60654902},
{"learn":[0.001829507846],"iteration":818,"passed_time":29.73611546,"remaining_time":6.571717824},
{"learn":[0.001817999098],"iteration":819,"passed_time":29.78410169,"remaining_time":6.537973541},
{"learn":[0.00180377096],"iteration":820,"passed_time":29.82933294,"remaining_time":6.503593905},
{"learn":[0.001794049223],"iteration":821,"passed_time":29.872676,"remaining_time":6.468778989},
{"learn":[0.001783666523],"iteration":822,"passed_time":29.9170005,"remaining_time":6.43415442},
{"learn":[0.001774824942],"iteration":823,"passed_time":29.96147078,"remaining_time":6.399537449},
{"learn":[0.00176131978],"iteration":824,"passed_time":30.00446612,"remaining_time":6.364583723},
{"learn":[0.001752501658],"iteration":825,"passed_time":30.04878121,"remaining_time":6.329888535},
{"learn":[0.001743034094],"iteration":826,"passed_time":30.09232885,"remaining_time":6.295009541},
{"learn":[0.001730246172],"iteration":827,"passed_time":30.13547151,"remaining_time":6.260025483},
{"learn":[0.001718123339],"iteration":828,"passed_time":30.18045736,"remaining_time":6.225401941},
{"learn":[0.001700274686],"iteration":829,"passed_time":30.22448648,"remaining_time":6.190557472},
{"learn":[0.001691550875],"iteration":830,"passed_time":30.26776157,"remaining_time":6.155537552},
{"learn":[0.001685578705],"iteration":831,"passed_time":30.31314327,"remaining_time":6.120923159},
{"learn":[0.001673633995],"iteration":832,"passed_time":30.36097761,"remaining_time":6.086774622},
{"learn":[0.001662217391],"iteration":833,"passed_time":30.40475536,"remaining_time":6.051785838},
{"learn":[0.001657590097],"iteration":834,"passed_time":30.45424436,"remaining_time":6.017904574},
{"learn":[0.001649625905],"iteration":835,"passed_time":30.50437209,"remaining_time":5.98411127},
{"learn":[0.001638183631],"iteration":836,"passed_time":30.54840847,"remaining_time":5.949092689},
{"learn":[0.001630930572],"iteration":837,"passed_time":30.5900878,"remaining_time":5.913596926},
{"learn":[0.001623364455],"iteration":838,"passed_time":30.62962211,"remaining_time":5.877674803},
{"learn":[0.001618987039],"iteration":839,"passed_time":30.67102925,"remaining_time":5.84210081},
{"learn":[0.001607606432],"iteration":840,"passed_time":30.71117281,"remaining_time":5.80627405},
{"learn":[0.001603418408],"iteration":841,"passed_time":30.7523541,"remaining_time":5.770631767},
{"learn":[0.001592502194],"iteration":842,"passed_time":30.79363353,"remaining_time":5.73499462},
{"learn":[0.001581321168],"iteration":843,"passed_time":30.83447253,"remaining_time":5.699262694},
{"learn":[0.001573436424],"iteration":844,"passed_time":30.8763851,"remaining_time":5.66371561},
{"learn":[0.001557639454],"iteration":845,"passed_time":30.91690664,"remaining_time":5.627900264},
{"learn":[0.001550102782],"iteration":846,"passed_time":30.95825902,"remaining_time":5.592223885},
{"learn":[0.001539273981],"iteration":847,"passed_time":31.0006607,"remaining_time":5.5567222},
{"learn":[0.001532887663],"iteration":848,"passed_time":31.04138994,"remaining_time":5.520906809},
{"learn":[0.001525877633],"iteration":849,"passed_time":31.08174333,"remaining_time":5.485013528},
{"learn":[0.001515432234],"iteration":850,"passed_time":31.12254961,"remaining_time":5.449189063},
{"learn":[0.001509548983],"iteration":851,"passed_time":31.16293391,"remaining_time":5.4132796},
{"learn":[0.001505608246],"iteration":852,"passed_time":31.20376608,"remaining_time":5.377436828},
{"learn":[0.001494957882],"iteration":853,"passed_time":31.24431867,"remaining_time":5.341534573},
{"learn":[0.001484880426],"iteration":854,"passed_time":31.28680275,"remaining_time":5.305949004},
{"learn":[0.001480069148],"iteration":855,"passed_time":31.32810747,"remaining_time":5.27014892},
{"learn":[0.001460813664],"iteration":856,"passed_time":31.36555227,"remaining_time":5.23369192},
{"learn":[0.001450992237],"iteration":857,"passed_time":31.40386223,"remaining_time":5.197375801},
{"learn":[0.001440685401],"iteration":858,"passed_time":31.44105221,"remaining_time":5.160871202},
{"learn":[0.001426532406],"iteration":859,"passed_time":31.47747543,"remaining_time":5.124240186},
{"learn":[0.001419662961],"iteration":860,"passed_time":31.51504924,"remaining_time":5.087795405},
{"learn":[0.001410416407],"iteration":861,"passed_time":31.55146669,"remaining_time":5.051162881},
{"learn":[0.001393089928],"iteration":862,"passed_time":31.588762,"remaining_time":5.014670213},
{"learn":[0.001384047035],"iteration":863,"passed_time":31.62629142,"remaining_time":4.978212539},
{"learn":[0.001380161151],"iteration":864,"passed_time":31.66409985,"remaining_time":4.941795931},
{"learn":[0.00136912778],"iteration":865,"passed_time":31.70347999,"remaining_time":4.905619306},
{"learn":[0.001365434463],"iteration":866,"passed_time":31.74051809,"remaining_time":4.869076017},
{"learn":[0.00135685902],"iteration":867,"passed_time":31.77741745,"remaining_time":4.832510487},
{"learn":[0.001348082528],"iteration":868,"passed_time":31.81455175,"remaining_time":4.795979609},
{"learn":[0.001338587962],"iteration":869,"passed_time":31.85364416,"remaining_time":4.759739932},
{"learn":[0.001326054403],"iteration":870,"passed_time":31.88969253,"remaining_time":4.723042866},
{"learn":[0.001310551372],"iteration":871,"passed_time":31.92639585,"remaining_time":4.686443427},
{"learn":[0.001304999482],"iteration":872,"passed_time":31.96334105,"remaining_time":4.649878938},
{"learn":[0.001301362778],"iteration":873,"passed_time":31.99960398,"remaining_time":4.613215219},
{"learn":[0.00129462358],"iteration":874,"passed_time":32.03557447,"remaining_time":4.576510639},
{"learn":[0.001281646646],"iteration":875,"passed_time":32.07325111,"remaining_time":4.540049244},
{"learn":[0.001273498477],"iteration":876,"passed_time":32.10814882,"remaining_time":4.503195331},
{"learn":[0.001265734692],"iteration":877,"passed_time":32.14196843,"remaining_time":4.466196069},
{"learn":[0.001251646179],"iteration":878,"passed_time":32.18186792,"remaining_time":4.430040977},
{"learn":[0.00124405579],"iteration":879,"passed_time":32.2225356,"remaining_time":4.393982127},
{"learn":[0.001235497241],"iteration":880,"passed_time":32.263029,"remaining_time":4.357889275},
{"learn":[0.001225595776],"iteration":881,"passed_time":32.3032136,"remaining_time":4.32174513},
{"learn":[0.001219923529],"iteration":882,"passed_time":32.3441844,"remaining_time":4.285696007},
{"learn":[0.001209381287],"iteration":883,"passed_time":32.38408307,"remaining_time":4.249495063},
{"learn":[0.00119851255],"iteration":884,"passed_time":32.42509153,"remaining_time":4.213429972},
{"learn":[0.001191399403],"iteration":885,"passed_time":32.46504841,"remaining_time":4.177218419},
{"learn":[0.001180565496],"iteration":886,"passed_time":32.50639356,"remaining_time":4.141175278},
{"learn":[0.001170865635],"iteration":887,"passed_time":32.54654413,"remaining_time":4.10496953},
{"learn":[0.001161622992],"iteration":888,"passed_time":32.58849993,"remaining_time":4.068980306},
{"learn":[0.001154375309],"iteration":889,"passed_time":32.62905108,"remaining_time":4.032804066},
{"learn":[0.001144146419],"iteration":890,"passed_time":32.67046022,"remaining_time":3.996722967},
{"learn":[0.001137765458],"iteration":891,"passed_time":32.71196455,"remaining_time":3.960641448},
{"learn":[0.001136268125],"iteration":892,"passed_time":32.75258984,"remaining_time":3.924442455},
{"learn":[0.00112738687],"iteration":893,"passed_time":32.79307033,"remaining_time":3.888216393},
{"learn":[0.001120479978],"iteration":894,"passed_time":32.83434785,"remaining_time":3.852074328},
{"learn":[0.001110872718],"iteration":895,"passed_time":32.87423677,"remaining_time":3.815759625},
{"learn":[0.0011073727],"iteration":896,"passed_time":32.9250806,"remaining_time":3.780694874},
{"learn":[0.001098858643],"iteration":897,"passed_time":32.96470519,"remaining_time":3.744320634},
{"learn":[0.001092278243],"iteration":898,"passed_time":33.00955037,"remaining_time":3.708525681},
{"learn":[0.001083253506],"iteration":899,"passed_time":33.04933267,"remaining_time":3.672148074},
{"learn":[0.001079947781],"iteration":900,"passed_time":33.09080465,"remaining_time":3.635948569},
{"learn":[0.00107395519],"iteration":901,"passed_time":33.13931836,"remaining_time":3.600502438},
{"learn":[0.001065647696],"iteration":902,"passed_time":33.18423537,"remaining_time":3.564641009},
{"learn":[0.001058957756],"iteration":903,"passed_time":33.22588109,"remaining_time":3.528412151},
{"learn":[0.001050428828],"iteration":904,"passed_time":33.26775466,"remaining_time":3.49219524},
{"learn":[0.001046810602],"iteration":905,"passed_time":33.31079346,"remaining_time":3.456086738},
{"learn":[0.001036379377],"iteration":906,"passed_time":33.35129935,"remaining_time":3.419703241},
{"learn":[0.001035063287],"iteration":907,"passed_time":33.39332322,"remaining_time":3.383464467},
{"learn":[0.001027306867],"iteration":908,"passed_time":33.43290932,"remaining_time":3.34696892},
{"learn":[0.001018159443],"iteration":909,"passed_time":33.47358569,"remaining_time":3.310574409},
{"learn":[0.001012336894],"iteration":910,"passed_time":33.51458287,"remaining_time":3.274201839},
{"learn":[0.001006690228],"iteration":911,"passed_time":33.55474546,"remaining_time":3.237738597},
{"learn":[0.0009995048081],"iteration":912,"passed_time":33.59556727,"remaining_time":3.201330068},
{"learn":[0.0009931661124],"iteration":913,"passed_time":33.64178436,"remaining_time":3.165419535},
{"learn":[0.0009852786246],"iteration":914,"passed_time":33.68422253,"remaining_time":3.129135426},
{"learn":[0.0009760597381],"iteration":915,"passed_time":33.72895665,"remaining_time":3.093048427},
{"learn":[0.0009699490684],"iteration":916,"passed_time":33.77363052,"remaining_time":3.056937114},
{"learn":[0.000968712218],"iteration":917,"passed_time":33.81768652,"remaining_time":3.020751955},
{"learn":[0.0009634111389],"iteration":918,"passed_time":33.86172743,"remaining_time":2.984548337},
{"learn":[0.0009566871328],"iteration":919,"passed_time":33.90478802,"remaining_time":2.948242437},
{"learn":[0.0009445688134],"iteration":920,"passed_time":33.94941349,"remaining_time":2.912056097},
{"learn":[0.0009413372881],"iteration":921,"passed_time":33.99578301,"remaining_time":2.875998997},
{"learn":[0.0009369333415],"iteration":922,"passed_time":34.04014199,"remaining_time":2.839751824},
{"learn":[0.0009309642811],"iteration":923,"passed_time":34.08461916,"remaining_time":2.803496814},
{"learn":[0.0009258649527],"iteration":924,"passed_time":34.12910403,"remaining_time":2.767224651},
{"learn":[0.0009175154758],"iteration":925,"passed_time":34.17512675,"remaining_time":2.731057645},
{"learn":[0.000909417172],"iteration":926,"passed_time":34.22110695,"remaining_time":2.694866027},
{"learn":[0.0009017904628],"iteration":927,"passed_time":34.26368939,"remaining_time":2.658389694},
{"learn":[0.0008958137878],"iteration":928,"passed_time":34.30862622,"remaining_time":2.622080153},
{"learn":[0.0008885171591],"iteration":929,"passed_time":34.35116887,"remaining_time":2.58557185},
{"learn":[0.0008873508474],"iteration":930,"passed_time":34.39945883,"remaining_time":2.549476541},
{"learn":[0.0008800578035],"iteration":931,"passed_time":34.4420961,"remaining_time":2.512942634},
{"learn":[0.0008788777626],"iteration":932,"passed_time":34.48199799,"remaining_time":2.476199213},
{"learn":[0.0008720583446],"iteration":933,"passed_time":34.52215427,"remaining_time":2.439467004},
{"learn":[0.0008663499687],"iteration":934,"passed_time":34.56324492,"remaining_time":2.402792427},
{"learn":[0.0008605265407],"iteration":935,"passed_time":34.60459731,"remaining_time":2.366126312},
{"learn":[0.00085618974],"iteration":936,"passed_time":34.64511178,"remaining_time":2.329393855},
{"learn":[0.0008551361223],"iteration":937,"passed_time":34.68606818,"remaining_time":2.292682545},
{"learn":[0.0008496279469],"iteration":938,"passed_time":34.72862232,"remaining_time":2.256065987},
{"learn":[0.0008431381249],"iteration":939,"passed_time":34.7745008,"remaining_time":2.219648987},
{"learn":[0.0008359365302],"iteration":940,"passed_time":34.81993306,"remaining_time":2.183183901},
{"learn":[0.0008324144929],"iteration":941,"passed_time":34.86496568,"remaining_time":2.146675169},
{"learn":[0.0008265928328],"iteration":942,"passed_time":34.90877195,"remaining_time":2.110074232},
{"learn":[0.0008222372534],"iteration":943,"passed_time":34.94982125,"remaining_time":2.073294481},
{"learn":[0.0008193376836],"iteration":944,"passed_time":34.9901977,"remaining_time":2.036466533},
{"learn":[0.0008154365648],"iteration":945,"passed_time":35.03544426,"remaining_time":1.99990908},
{"learn":[0.0008144201686],"iteration":946,"passed_time":35.07587728,"remaining_time":1.963063882},
{"learn":[0.0008135203373],"iteration":947,"passed_time":35.1164628,"remaining_time":1.926219478},
{"learn":[0.00080799938],"iteration":948,"passed_time":35.15583508,"remaining_time":1.88930199},
{"learn":[0.000804262251],"iteration":949,"passed_time":35.19582615,"remaining_time":1.852411903},
{"learn":[0.0007988787724],"iteration":950,"passed_time":35.23670716,"remaining_time":1.815561147},
{"learn":[0.0007935681062],"iteration":951,"passed_time":35.27658922,"remaining_time":1.778651557},
{"learn":[0.0007899661015],"iteration":952,"passed_time":35.31673592,"remaining_time":1.741748781},
{"learn":[0.0007877421478],"iteration":953,"passed_time":35.35854801,"remaining_time":1.704919506},
{"learn":[0.0007850271159],"iteration":954,"passed_time":35.39854351,"remaining_time":1.667994197},
{"learn":[0.0007795971863],"iteration":955,"passed_time":35.43889794,"remaining_time":1.631078985},
{"learn":[0.0007744622302],"iteration":956,"passed_time":35.4786818,"remaining_time":1.594130948},
{"learn":[0.0007710269733],"iteration":957,"passed_time":35.52108044,"remaining_time":1.557291627},
{"learn":[0.0007689059046],"iteration":958,"passed_time":35.56100472,"remaining_time":1.520334925},
{"learn":[0.0007639785875],"iteration":959,"passed_time":35.60028041,"remaining_time":1.483345017},
{"learn":[0.0007614258908],"iteration":960,"passed_time":35.63958987,"remaining_time":1.446351722},
{"learn":[0.0007593472502],"iteration":961,"passed_time":35.68065895,"remaining_time":1.409423119},
{"learn":[0.0007541318344],"iteration":962,"passed_time":35.72204164,"remaining_time":1.372497966},
{"learn":[0.0007493290293],"iteration":963,"passed_time":35.76458574,"remaining_time":1.335606936},
{"learn":[0.0007473284527],"iteration":964,"passed_time":35.80488293,"remaining_time":1.298622697},
{"learn":[0.0007425153828],"iteration":965,"passed_time":35.84176295,"remaining_time":1.261511325},
{"learn":[0.0007401976622],"iteration":966,"passed_time":35.88422653,"remaining_time":1.224590978},
{"learn":[0.0007382739177],"iteration":967,"passed_time":35.92090306,"remaining_time":1.18746787},
{"learn":[0.000733484948],"iteration":968,"passed_time":35.95697344,"remaining_time":1.150326292},
{"learn":[0.0007275656906],"iteration":969,"passed_time":35.99486242,"remaining_time":1.113243167},
{"learn":[0.0007231712992],"iteration":970,"passed_time":36.0313307,"remaining_time":1.076115953},
{"learn":[0.000717865856],"iteration":971,"passed_time":36.06827551,"remaining_time":1.039003821},
{"learn":[0.000713236346],"iteration":972,"passed_time":36.10465276,"remaining_time":1.001876284},
{"learn":[0.0007087983528],"iteration":973,"passed_time":36.14177707,"remaining_time":0.9647702297},
{"learn":[0.0007062888761],"iteration":974,"passed_time":36.17513383,"remaining_time":0.9275675341},
{"learn":[0.0007018394968],"iteration":975,"passed_time":36.20992483,"remaining_time":0.8904079877},
{"learn":[0.0007000229833],"iteration":976,"passed_time":36.24645586,"remaining_time":0.8532942526},
{"learn":[0.0006979143426],"iteration":977,"passed_time":36.28426629,"remaining_time":0.8162104892},
{"learn":[0.0006928215237],"iteration":978,"passed_time":36.32135485,"remaining_time":0.7791097567},
{"learn":[0.0006885540145],"iteration":979,"passed_time":36.35792612,"remaining_time":0.7419984923},
{"learn":[0.0006862363054],"iteration":980,"passed_time":36.39360359,"remaining_time":0.7048710175},
{"learn":[0.0006842073398],"iteration":981,"passed_time":36.42882179,"remaining_time":0.6677380777},
{"learn":[0.000679860581],"iteration":982,"passed_time":36.46270145,"remaining_time":0.6305858847},
{"learn":[0.0006757461085],"iteration":983,"passed_time":36.50085248,"remaining_time":0.5935097964},
{"learn":[0.0006740549231],"iteration":984,"passed_time":36.55412292,"remaining_time":0.5566617703},
{"learn":[0.0006721133643],"iteration":985,"passed_time":36.58971578,"remaining_time":0.519529433},
{"learn":[0.0006654750753],"iteration":986,"passed_time":36.63277772,"remaining_time":0.482498592},
{"learn":[0.0006614789321],"iteration":987,"passed_time":36.67091367,"remaining_time":0.4453957125},
{"learn":[0.0006553779548],"iteration":988,"passed_time":36.7110636,"remaining_time":0.4083131442},
{"learn":[0.0006513517824],"iteration":989,"passed_time":36.75276811,"remaining_time":0.3712400819},
{"learn":[0.0006452979092],"iteration":990,"passed_time":36.79292104,"remaining_time":0.3341435816},
{"learn":[0.0006445313571],"iteration":991,"passed_time":36.83285428,"remaining_time":0.2970391474},
{"learn":[0.0006405007849],"iteration":992,"passed_time":36.87408028,"remaining_time":0.2599381289},
{"learn":[0.0006397652756],"iteration":993,"passed_time":36.91387238,"remaining_time":0.2228201552},
{"learn":[0.0006366868877],"iteration":994,"passed_time":36.95659953,"remaining_time":0.1857115554},
{"learn":[0.0006359877336],"iteration":995,"passed_time":36.99656891,"remaining_time":0.148580598},
{"learn":[0.0006302402668],"iteration":996,"passed_time":37.03622317,"remaining_time":0.1114429985},
{"learn":[0.0006271413004],"iteration":997,"passed_time":37.07801581,"remaining_time":0.0743046409},
{"learn":[0.0006264698721],"iteration":998,"passed_time":37.11833416,"remaining_time":0.03715548964},
{"learn":[0.0006225395537],"iteration":999,"passed_time":37.15781087,"remaining_time":0}
]}